[{"id":"V_NnSaWRLDk","title":"【ライブカメラ】夏休みも もうすぐ終わり「白浜大浜ビーチ」・静岡県 下田市／2025年8月30日(土)","date":"2025-08-29","sec":18991},{"id":"gqZNR6Epw80","title":"【ライブ配信終了】最新天気ニュース・地震情報 2025年8月30日(土)／40℃に迫る危険な暑さ〈ウェザーニュースLiVEモーニング・松本真央／内藤邦裕〉","date":"2025-08-29","sec":12579,"caster":"松本 真央","weather":"内藤邦裕"},{"id":"kMtxmFnsTrY","title":"【ライブカメラ】幕張から東京・千葉の夜景／千葉県千葉市美浜区 ウェザーニュースお天気カメラ 2025年8月29日(金)","date":"2025-08-29","sec":38214},{"id":"6FNqObePmYY","title":"【ライブ配信終了】最新天気ニュース・地震情報 2025年8月30日(土)1:00〜／宮城県沖でM5.7の地震 福島県沖でM4.7の地震　青森県で大雨 土砂災害や河川増水に警戒　ウェザーニュースLiVE","date":"2025-08-29","sec":14273},{"id":"sXV5WOj7v-M","title":"【ライブ配信終了】最新天気ニュース・地震情報 2025年8月29日(金)21:30~／青森県で線状降水帯による大雨〈ウェザーニュースLiVEムーン・駒木結衣／宇野沢達也〉","date":"2025-08-29","sec":11897,"caster":"駒木 結衣","weather":"宇野沢達也"},{"id":"6b34GDVQ-lk","title":"【JR東日本×ウェザーニュース】避暑旅タイアップ特別企画　第11回出演：駒木結衣、小川千奈","date":"2025-08-29","sec":2810,"caster":"小川 千奈"},{"id":"LtJoF9nRlY0","title":"【ライブ配信終了】最新天気ニュース・地震情報 2025年8月29日(金)／8月最後の週末も猛暑〈ウェザーニュースLiVEムーン・駒木 結衣／宇野沢 達也〉","date":"2025-08-29","sec":4298,"caster":"駒木 結衣","weather":"宇野沢達也"},{"id":"wnDIwzaB08k","title":"【ライブ配信終了】最新天気ニュース・地震情報 2025年8月29日(金)／8月最後の週末も猛暑〈ウェザーニュースLiVEイブニング・岡本結子リサ／宇野沢達也〉","date":"2025-08-29","sec":12424,"caster":"岡本 結子 リサ","weather":"宇野沢達也"},{"id":"7U4dAQvN0WE","title":"【ライブ配信終了】最新天気ニュース・地震情報 2025年8月29日(金)／西日本と東海の猛暑止まらず　北日本は夕方以降一部で雨に＜ウェザーニュースLiVEアフタヌーン・白井ゆかり／宇野沢達也〉","date":"2025-08-29","sec":12749,"caster":"白井 ゆかり","weather":"宇野沢達也"},{"id":"c4F4TGqCPew","title":"【ライブ配信終了】最新天気ニュース・地震情報 2025年8月29日(金)／関東以西の猛暑止まらず　北日本は夕方以降一部で雨に〈ウェザーニュースLiVEコーヒータイム・川畑 玲／山口 剛央〉","date":"2025-08-29","sec":12642,"caster":"川畑 玲","weather":"山口剛央"},{"id":"uz6vkmwVMw0","title":"【気候変動番組】100年天気予報~雨が増えても“水不足”？干ばつの知られざるリスク~/2025年8月29日(金)12:00~/魚住茉由・吉良真由子","date":"2025-08-29","sec":2117,"caster":"魚住 茉由"},{"id":"ysbWrnX5_64","title":"【ライブ配信終了】最新天気ニュース・地震情報 2025年8月29日(金)／西日本や東海は猛暑続く　北日本は雨風が強まるおそれ〈ウェザーニュースLiVEサンシャイン・青原桃香／山口剛央〉","date":"2025-08-28","sec":12538,"caster":"青原 桃香","weather":"山口剛央"},{"id":"47nFYhgCbjE","title":"【ライブ配信終了】最新天気ニュース・地震情報 2025年8月29日(金)／西日本と東海の猛暑止まらず　北日本は夕方以降一部で雨に〈ウェザーニュースLiVEモーニング・松本真央／山口剛央〉","date":"2025-08-28","sec":12375,"caster":"松本 真央","weather":"山口剛央"},{"id":"D1zNbCjCmQI","title":"【ライブ配信終了】最新天気ニュース・地震情報 2025年8月29日(金) 1:00〜／西日本と東海の猛暑止まらず　北日本は夕方以降一部で雨に〈ウェザーニュースLiVE〉","date":"2025-08-28","sec":14535},{"id":"5kP0wnh9fk8","title":"【ライブ配信終了】最新天気ニュース・地震情報 2025年8月28日(木)／明日も厳しい暑さ続く〈ウェザーニュースLiVEムーン・山岸 愛梨／本田 竜也〉","date":"2025-08-28","sec":18545,"caster":"山岸 愛梨","weather":"本田竜也"},{"id":"g2jx-ybnReU","title":"【ライブ配信終了】最新天気ニュース・地震情報 2025年8月28日(木)／関東は雲が広がり暑さ落ち着く　東海以西は猛暑日の所〈ウェザーニュースLiVEイブニング・駒木結衣／本田竜也〉","date":"2025-08-28","sec":12889,"caster":"駒木 結衣","weather":"本田竜也"},{"id":"HrrAHw5r7Z0","title":"【ライブ配信終了】最新天気ニュース・地震情報 2025年8月28日(木)／関東は雲が広がり暑さ落ち着く　東海以西は猛暑日の所も＜ウェザーニュースLiVEアフタヌーン・白井ゆかり／本田竜也〉","date":"2025-08-28","sec":12534,"caster":"白井 ゆかり","weather":"本田竜也"},{"id":"bKwlFCvLQRA","title":"【ライブ配信終了】最新天気ニュース・地震情報 2025年8月28日(木)／関東は雲が広がり暑さ落ち着く　東海以西は猛暑日の所も〈ウェザーニュースLiVEコーヒータイム・白井ゆかり／山口剛央〉","date":"2025-08-28","sec":12125,"caster":"白井 ゆかり","weather":"山口剛央"},{"id":"j4BnK4I49n0","title":"【ライブ配信終了】最新天気ニュース・地震情報 2025年8月28日(木)／関東は雲が広がり暑さ落ち着く　東海以西は猛暑日の所も〈ウェザーニュースLiVEサンシャイン・小林李衣奈／山口剛央〉","date":"2025-08-27","sec":12709,"caster":"小林 李衣奈","weather":"山口剛央"},{"id":"FnlDrYyGADk","title":"【ライブ配信終了】最新天気ニュース・地震情報 2025年8月28日(木)／関東は雲が広がり暑さ落ち着く　東海以西は猛暑日の所も〈ウェザーニュースLiVEモーニング・福吉貴文／山口剛央〉","date":"2025-08-27","sec":12552,"caster":"福吉 貴文","weather":"山口剛央"},{"id":"Yre6MSbNwqU","title":"【ライブ配信終了】最新天気ニュース・地震情報 2025年8月28日(木) 1:00〜／関東は雲が広がり暑さ落ち着く　東海以西は猛暑日の所も〈ウェザーニュースLiVE〉","date":"2025-08-27","sec":14767},{"id":"foj1ylbd4IQ","title":"【ライブ配信終了】最新天気ニュース・地震情報 2025年8月27日(水)／あす関東は雲が広がり暑さ落ち着く　東海以西は猛暑日の所も〈ウェザーニュースLiVEムーン・山岸 愛梨／宇野沢 達也〉","date":"2025-08-27","sec":18678,"caster":"山岸 愛梨","weather":"宇野沢達也"},{"id":"qomtK7585tA","title":"【ライブ配信終了】最新天気ニュース・地震情報 2025年8月27日(水)／近畿、東海では局地的に雨雲が発達〈ウェザーニュースLiVEイブニング・戸北美月／宇野沢達也〉","date":"2025-08-27","sec":13278,"caster":"戸北 美月","weather":"宇野沢達也"},{"id":"uAHsQSv5H_U","title":"【雷ライブカメラ】東京都・埼玉県ソラカメ／関東でゲリラ雷雨、停電・冠水に注意　#ライブカメラ　2025年8月27日(水)","date":"2025-08-27","sec":4154},{"id":"9gkDWLiY01c","title":"【ライブカメラ】関東ゲリラ雷雨／千葉県千葉市美浜区 ウェザーニュースお天気カメラ 2025年8月27日(水)","date":"2025-08-27","sec":4159},{"id":"1Mm17JyBlF0","title":"【ライブ配信終了】最新天気ニュース・地震情報 2025年8月27日(水)／北海道や東北北部で大雨警戒　前線南下で雨のエリア拡大＜ウェザーニュースLiVEアフタヌーン・田辺真南葉／宇野沢達也〉","date":"2025-08-27","sec":11684,"caster":"田辺 真南葉","weather":"宇野沢達也"},{"id":"z4-MsmF8Xfs","title":"【ライブ配信終了】最新天気ニュース・地震情報 2025年8月27日(水)／北海道や東北北部で大雨警戒　前線南下で雨のエリア拡大〈ウェザーニュースLiVEコーヒータイム・魚住茉由／飯島栄一〉","date":"2025-08-27","sec":12111,"caster":"魚住 茉由","weather":"飯島栄一"},{"id":"tu4jZdhgoks","title":"【ライブカメラ】夏休みももうすぐ終わり「白浜大浜ビーチ」・静岡県 下田市／2025年8月27日(水)","date":"2025-08-26","sec":39733},{"id":"NR2yd6jcOxo","title":"【ライブ配信終了】最新天気ニュース・地震情報 2025年8月27日(水)／北海道や東北北部で大雨警戒　関東など太平洋側は猛暑継続〈ウェザーニュースLiVEサンシャイン・松本真央／飯島栄一〉","date":"2025-08-26","sec":12004,"caster":"松本 真央","weather":"飯島栄一"},{"id":"x-LtAFjho8c","title":"【ライブ配信終了】最新天気ニュース・地震情報 2025年8月27日(水)／前線南下で雨のエリア拡大　関東など太平洋側は猛暑継続〈ウェザーニュースLiVEモーニング・小林李衣奈／飯島栄一〉","date":"2025-08-26","sec":12616,"caster":"小林 李衣奈","weather":"飯島栄一"},{"id":"o8ItuHozMKY","title":"【ライブカメラ】幕張から東京・千葉の夜景／千葉県千葉市美浜区 ウェザーニュースお天気カメラ 2025年8月26日(火)","date":"2025-08-26","sec":34089},{"id":"Hj8ptI4RVyY","title":"【ライブ配信終了】最新天気ニュース・地震情報 2025年8月27日(水) 1:00〜／厳しい暑さと強雨に注意〈ウェザーニュースLiVE〉","date":"2025-08-26","sec":13954},{"id":"MQ_YRGEpoIo","title":"【#雨雲レーダー ライブ】各地でゲリラ雷雨に注意 #ライブカメラ タイプラプス／雨雲レーダー 4画面監視　2025年8月26日(火)","date":"2025-08-26","sec":42901},{"id":"xCNAKMDRytI","title":"【ライブ配信終了】最新天気ニュース・地震情報 2025年8月26日(火)／明日朝にかけ北海道の広範囲で大雨警戒　線状降水帯の形成も〈ウェザーニュースLiVEムーン・岡本結子リサ／宇野沢達也〉","date":"2025-08-26","sec":19111,"caster":"岡本 結子 リサ","weather":"宇野沢達也"},{"id":"GODPVCb38vE","title":"【ライブ配信終了】最新天気ニュース・地震情報 2025年8月26日(火)／西日本、東日本は暑さと雷雨注意　北海道は局地的な大雨に〈ウェザーニュースLiVEイブニング・戸北美月／宇野沢達也〉","date":"2025-08-26","sec":12606,"caster":"戸北 美月","weather":"宇野沢達也"},{"id":"WgVQQrYzS-c","title":"【ライブ配信終了】最新天気ニュース・地震情報 2025年8月26日(火)／西日本、東日本は暑さと雷雨注意　北海道は局地的な大雨に＜ウェザーニュースLiVEアフタヌーン・山岸愛梨／宇野沢達也〉","date":"2025-08-26","sec":12761,"caster":"山岸 愛梨","weather":"宇野沢達也"},{"id":"8hreLilcbBk","title":"【ライブ配信終了】最新天気ニュース・地震情報 2025年8月26日(火)／西日本や東日本は暑さと雷雨注意　北海道は局地的な大雨に〈ウェザーニュースLiVEコーヒータイム・田辺真南葉／飯島栄一〉","date":"2025-08-26","sec":12561,"caster":"田辺 真南葉","weather":"飯島栄一"},{"id":"w9wN8GYgGyI","title":"【ライブカメラ】夏休みももうすぐ終わり「白浜大浜ビーチ」・静岡県 下田市／2025年8月26日(火)","date":"2025-08-25","sec":42900},{"id":"BEizM8K4Lxg","title":"【ライブ配信終了】最新天気ニュース・地震情報 2025年8月26日(火)／西日本、東日本は暑さと雷雨注意　北海道は局地的な大雨に〈ウェザーニュースLiVEサンシャイン・小林李衣奈／飯島栄一〉","date":"2025-08-25","sec":11599,"caster":"小林 李衣奈","weather":"飯島栄一"},{"id":"MlvMl7iSCWE","title":"【ライブ配信終了】最新天気ニュース・地震情報 2025年8月26日(火)／西日本、東日本は暑さと雷雨注意　北海道は局地的な大雨に〈ウェザーニュースLiVEモーニング・魚住茉由／飯島栄一〉","date":"2025-08-25","sec":12723,"caster":"魚住 茉由","weather":"飯島栄一"},{"id":"f9C2OnMIIAU","title":"【ライブ配信終了】最新天気ニュース・地震情報 2025年8月26日(火) 1:00〜／〈ウェザーニュースLiVE〉","date":"2025-08-25","sec":14265},{"id":"DtOMenkF4mM","title":"【ライブカメラ】幕張から東京・千葉の夜景／千葉県千葉市美浜区 ウェザーニュースお天気カメラ 2025年8月25日(月)","date":"2025-08-25","sec":23129},{"id":"aJftXYc-_5A","title":"【ライブ配信終了】最新天気ニュース・地震情報 2025年8月25日(月)／局地的に強まる雨に注意〈ウェザーニュースLiVEムーン・戸北美月／山口剛央〉","date":"2025-08-25","sec":19129,"caster":"戸北 美月","weather":"山口剛央"},{"id":"DIVGJW6L3W0","title":"【#雨雲レーダー ライブ】各地でゲリラ雷雨に注意 #ライブカメラ ／雨雲レーダー 4画面監視　2025年8月25日(月)","date":"2025-08-25","sec":33465},{"id":"DGdpmCvAENQ","title":"【ライブ配信終了】最新天気ニュース・地震情報 2025年8月25日(月)／〈ウェザーニュースLiVEイブニング・駒木 結衣／山口 剛央〉","date":"2025-08-25","sec":12784,"caster":"駒木 結衣","weather":"山口剛央"},{"id":"CryBpfkT1VU","title":"【ライブ配信終了】最新天気ニュース・地震情報 2025年8月25日(月)／西日本や東日本は酷暑の週明け　北海道は雨の可能性＜ウェザーニュースLiVEアフタヌーン・青原桃香／山口剛央〉","date":"2025-08-25","sec":11682,"caster":"青原 桃香","weather":"山口剛央"},{"id":"GVXjuXWicQU","title":"【ライブ配信終了】最新天気ニュース・地震情報 2025年8月25日(月)／西日本や東日本は酷暑の週明け　北海道は雨の可能性〈ウェザーニュースLiVEコーヒータイム・白井ゆかり／本田竜也〉","date":"2025-08-25","sec":12643,"caster":"白井 ゆかり","weather":"本田竜也"},{"id":"h6cFBSzEEC4","title":"【ライブカメラ】夏休みももうすぐ終わり「白浜大浜ビーチ」・静岡県 下田市／2025年8月25日(月)","date":"2025-08-24","sec":42899},{"id":"7JXwvOAr24Y","title":"【ライブ配信終了】最新天気ニュース・地震情報 2025年8月25日(月)／西日本や東日本は酷暑の週明け　北海道は雨の可能性〈ウェザーニュースLiVEサンシャイン・小林李衣奈／本田竜也〉","date":"2025-08-24","sec":12135,"caster":"小林 李衣奈","weather":"本田竜也"},{"id":"7aRnvftVKeU","title":"【ライブ配信終了】最新天気ニュース・地震情報 2025年8月25日(月)／西日本や東日本は酷暑の週明け　北海道は雨の可能性〈ウェザーニュースLiVEモーニング・魚住茉由／本田竜也〉","date":"2025-08-24","sec":12312,"caster":"魚住 茉由","weather":"本田竜也"},{"id":"nM79oNwUh30","title":"【ライブ配信終了】最新天気ニュース・地震情報 2025年8月25日(月) 1:00〜／酷暑の週明け　北海道は雲多く雨の可能性〈ウェザーニュースLiVE〉","date":"2025-08-24","sec":13269},{"id":"QMzYLRx0ha4","title":"【ライブカメラ】幕張から東京・千葉の夜景／千葉県千葉市美浜区 ウェザーニュースお天気カメラ 2025年8月24日(月)","date":"2025-08-24","sec":26415},{"id":"4Q56F8FiGOw","title":"【ライブ】最新天気ニュース・地震情報 2025年8月24日(日)／酷暑の週明け 北海道は雲多く雨の可能性〈ウェザーニュースLiVEムーン・岡本結子リサ／森田清輝〉","date":"2025-08-24","sec":19308,"caster":"岡本 結子 リサ","weather":"森田清輝"},{"id":"xqrQuoZnVSk","title":"【ライブ配信終了】最新天気ニュース・地震情報 2025年8月24日(日)／東日本は猛烈な残暑　西日本は変わりやすい空〈ウェザーニュースLiVEイブニング・山岸 愛梨／森田 清輝〉","date":"2025-08-24","sec":11239,"caster":"山岸 愛梨","weather":"森田清輝"},{"id":"HeeoCOjhngg","title":"【ライブ配信終了】最新天気ニュース・地震情報 2025年8月24日(日)／東日本は猛烈な残暑　西日本は変わりやすい空＜ウェザーニュースLiVEアフタヌーン・青原桃香／森田清輝〉","date":"2025-08-24","sec":11849,"caster":"青原 桃香","weather":"森田清輝"},{"id":"59C1FLSn2u4","title":"【ライブ配信終了】最新天気ニュース・地震情報 2025年8月24日(日)／東日本は猛烈な残暑　西日本は変わりやすい空〈ウェザーニュースLiVEコーヒータイム・松本真央／山口剛央〉","date":"2025-08-24","sec":12468,"caster":"松本 真央","weather":"山口剛央"},{"id":"eQ_4YNx8g1U","title":"【ライブカメラ】夏休みももうすぐ終わり「白浜大浜ビーチ」・静岡県 下田市／2025年8月24日(日)","date":"2025-08-23","sec":42899},{"id":"qUjYbH8yZPc","title":"【ライブ配信終了】最新天気ニュース・地震情報 2025年8月24日(日)／東日本は猛烈な残暑　西日本は変わりやすい空〈ウェザーニュースLiVEサンシャイン・川畑玲 ／山口剛央〉","date":"2025-08-23","sec":12062,"caster":"川畑 玲","weather":"山口剛央"},{"id":"QrarQx7sRk0","title":"【ライブ配信終了】最新天気ニュース・地震情報 2025年8月24日(日)／東日本は猛烈な残暑　西日本は変わりやすい空〈ウェザーニュースLiVEモーニング・田辺真南葉／山口剛央〉","date":"2025-08-23","sec":12837,"caster":"田辺 真南葉","weather":"山口剛央"},{"id":"zybloajk5UM","title":"【ライブ配信終了】最新天気ニュース・地震情報 2025年8月24日(日) 1:00〜／東日本は猛烈な残暑　西日本は変わりやすい空〈ウェザーニュースLiVE〉","date":"2025-08-23","sec":14238},{"id":"48aSt1MbG18","title":"【ライブ】最新天気ニュース・地震情報 2025年8月23日(土)／〈ウェザーニュースLiVEムーン・山岸 愛梨／森田 清輝〉","date":"2025-08-23","sec":18793,"caster":"山岸 愛梨","weather":"森田清輝"},{"id":"8M1QR_cHKps","title":"【ライブ配信終了】最新天気ニュース・地震情報 2025年8月23日(土)／あすも猛烈な残暑とゲリラ雷雨に注意〈ウェザーニュースLiVEイブニング・青原 桃香／森田 清輝〉","date":"2025-08-23","sec":11638,"caster":"青原 桃香","weather":"森田清輝"},{"id":"uNZcPRCvBDc","title":"【ライブ配信終了】最新天気ニュース・地震情報 2025年8月23日(土)／関東、東海など危険な暑さ 九州や中国、四国は一時的に雨＜ウェザーニュースLiVEアフタヌーン・松本真央／森田清輝〉","date":"2025-08-23","sec":11765,"caster":"松本 真央","weather":"森田清輝"},{"id":"APy3GpaPFVo","title":"【ライブ配信終了】最新天気ニュース・地震情報 2025年8月23日(土)／関東、東海など危険な暑さ 九州や中国、四国は一時的に雨〈ウェザーニュースLiVEコーヒータイム・魚住茉由／山口剛央〉","date":"2025-08-23","sec":12330,"caster":"魚住 茉由","weather":"山口剛央"},{"id":"BE-o0bWpz3Y","title":"【ライブカメラ】夏休みももうすぐ終わり「白浜大浜ビーチ」・静岡県 下田市／2025年8月23日(土)","date":"2025-08-22","sec":42900},{"id":"htVaqEIYEq4","title":"【ライブ配信終了】最新天気ニュース・地震情報 2025年8月23日(土)／関東、東海など危険な暑さ 九州や中国、四国は一時的に雨〈ウェザーニュースLiVEサンシャイン・小川千奈 ／山口剛央〉","date":"2025-08-22","sec":12640,"caster":"小川 千奈","weather":"山口剛央"},{"id":"UfET1KPyINE","title":"【ライブ配信終了】最新天気ニュース・地震情報 2025年8月23日(土)／危険な暑さ 北海道は朝まで雨〈ウェザーニュースLiVEモーニング・田辺真南葉／山口剛央〉","date":"2025-08-22","sec":12563,"caster":"田辺 真南葉","weather":"山口剛央"},{"id":"TQgsHyFUtHc","title":"【ライブカメラ】幕張から東京・千葉の夜景／千葉県千葉市美浜区 ウェザーニュースお天気カメラ 2025年8月22日(金)","date":"2025-08-22","sec":32986},{"id":"LZhUCl_uh0k","title":"【ライブ配信終了】最新天気ニュース・地震情報 2025年8月23日(土) 1:00〜／関東や東海など危険な暑さ 北海道は朝まで雨〈ウェザーニュースLiVE〉","date":"2025-08-22","sec":14441},{"id":"dmHdr-EhVCs","title":"【ライブ配信終了】最新天気ニュース・地震情報 2025年8月22日(金)21:30〜／北海道では明日朝にかけて雨〈ウェザーニュースLiVEムーン・駒木結衣／内藤邦裕〉","date":"2025-08-22","sec":11862,"caster":"駒木 結衣","weather":"内藤邦裕"},{"id":"g42scCxCoqE","title":"【JR東日本×ウェザーニュース】避暑旅タイアップ特別企画　第10回出演：駒木結衣","date":"2025-08-22","sec":2749,"caster":"駒木 結衣"},{"id":"dvuLUDWo-mA","title":"【台風雨風ライブカメラ】九州南部は激しい雨に注意／台風12号は九州を抜けて日向灘へ 2025年8月22日(金) 鹿児島県枕崎市 ＜ヤッシーの様子＞","date":"2025-08-22","sec":39754},{"id":"J6nbiT10FfI","title":"【ライブ配信終了】最新天気ニュース・地震情報 2025年8月22日(金)／北海道では明日朝にかけて雨〈ウェザーニュースLiVEムーン・駒木結衣／内藤邦裕〉","date":"2025-08-22","sec":4490,"caster":"駒木 結衣","weather":"内藤邦裕"},{"id":"_aAS3_u0hIA","title":"【ライブ配信終了】最新天気ニュース・地震情報 2025年8月22日(金)／台風12号は熱帯低気圧に　引き続き九州は強雨に注意〈ウェザーニュースLiVEイブニング・戸北 美月／内藤 邦裕〉","date":"2025-08-22","sec":11431,"caster":"戸北 美月","weather":"内藤邦裕"},{"id":"EOu_nwXLxG8","title":"【ライブ配信終了】最新天気ニュース・地震情報 2025年8月22日(金)／台風12号は熱帯低気圧に　引き続き九州は強雨に注意＜ウェザーニュースLiVEアフタヌーン・青原桃香／内藤邦裕〉","date":"2025-08-22","sec":11058,"caster":"青原 桃香","weather":"内藤邦裕"},{"id":"ffOJ9FxseYY","title":"【ライブ配信終了】最新天気ニュース・地震情報 2025年8月22日(金)／台風12号は熱帯低気圧に　引き続き九州は強雨に注意〈ウェザーニュースLiVEコーヒータイム・魚住茉由／山口剛央〉","date":"2025-08-22","sec":11654,"caster":"魚住 茉由","weather":"山口剛央"},{"id":"bf9iy84ZM1k","title":"【ライブ配信終了】最新天気ニュース・地震情報 2025年8月22日(金)／九州は台風12号の影響で強雨注意 関東から西は厳しい暑さ　〈ウェザーニュースLiVEサンシャイン・川畑玲 ／山口剛央〉","date":"2025-08-21","sec":12334,"caster":"川畑 玲","weather":"山口剛央"},{"id":"8K57LuY-Gis","title":"【台風雨風ライブカメラ】九州南部は大雨災害に警戒／台風12号発生･鹿児島県に上陸 2025年8月21日(木) 鹿児島県枕崎市 ＜ヤッシーの様子＞","date":"2025-08-21","sec":42899},{"id":"NMkd1Mxjwcs","title":"【ライブ配信終了】台風12号が九州南部を東進　引き続き強雨に注意／最新天気ニュース・地震情報 2025年8月22日(金)〈ウェザーニュースLiVEモーニング・福吉貴文／山口剛央〉","date":"2025-08-21","sec":13298,"caster":"福吉 貴文","weather":"山口剛央"},{"id":"25oYDy4q4e0","title":"【ライブ配信終了】最新天気ニュース・地震情報 2025年8月22日(金) 1:00〜／台風12号九州南部を東進〈ウェザーニュースLiVE〉","date":"2025-08-21","sec":15321},{"id":"OkQN-ATlBY8","title":"【ライブ配信終了】最新天気ニュース・地震情報 2025年8月21日(木)／台風12号　明日にかけ大雨警戒〈ウェザーニュースLiVEムーン・山岸愛梨／本田 竜也〉","date":"2025-08-21","sec":17990,"caster":"山岸 愛梨","weather":"本田竜也"},{"id":"XiQfsXMz38g","title":"【台風雨風ライブカメラ】九州南部は大雨災害に警戒／台風12号発生･鹿児島県に上陸 2025年8月21日(木) 鹿児島県枕崎市 ＜ヤッシーの様子＞","date":"2025-08-21","sec":41280},{"id":"T4vVeT5DUDI","title":"【ライブ配信終了】最新天気ニュース・地震情報 2025年8月21日(木)／台風12号 明日にかけて大雨に警戒〈ウェザーニュースLiVEイブニング・駒木結衣／本田竜也〉","date":"2025-08-21","sec":12298,"caster":"駒木 結衣","weather":"本田竜也"},{"id":"ZnJRV3hWC18","title":"【ライブ配信終了】最新天気ニュース・地震情報 2025年8月21日(木)／台風12号発生 九州は今日〜明日にかけて大雨のおそれ＜ウェザーニュースLiVEアフタヌーン・田辺真南葉／本田竜也〉","date":"2025-08-21","sec":11564,"caster":"田辺 真南葉","weather":"本田竜也"},{"id":"nsLlqOh-SVg","title":"【ライブ配信終了】最新天気ニュース・地震情報 2025年8月21日(木)／台風12号発生 九州は今日〜明日にかけて大雨のおそれ〈ウェザーニュースLiVEコーヒータイム・白井ゆかり／芳野達郎〉","date":"2025-08-21","sec":12550,"caster":"白井 ゆかり","weather":"芳野達郎"},{"id":"Nzcl6-8iyeo","title":"【4画面ライブ】東北は線状降水帯発生による大雨のおそれ／雨雲レーダー監視　2025年8月21日(木)","date":"2025-08-20","sec":31533},{"id":"SHoBN3BAt1E","title":"【ライブ配信終了】最新天気ニュース・地震情報 2025年8月21日(木)／九州東シナ海側は強雨に注意 東北北部は天気回復へ〈ウェザーニュースLiVEサンシャイン・江川清音／芳野達郎〉","date":"2025-08-20","sec":12742,"caster":"江川 清音","weather":"芳野達郎"},{"id":"kDVAjwahnDQ","title":"【ライブ配信終了】最新天気ニュース・地震情報 2025年8月21日(木)／終わりの見えない残暑　東北北部は天気回復へ〈ウェザーニュースLiVEモーニング・小林李衣奈／芳野達郎〉","date":"2025-08-20","sec":12339,"caster":"小林 李衣奈","weather":"芳野達郎"},{"id":"FAdWYKr8Czo","title":"【ライブ】最新天気ニュース・地震情報 2025年8月21日(木)1:00〜／東北は大雨災害に警戒　線状降水帯発生のおそれ〈ウェザーニュースLiVE〉","date":"2025-08-20","sec":14365},{"id":"jdv_ziuDHbY","title":"【ライブ配信終了】最新天気ニュース・地震情報 2025年8月20日(水)／秋田県仙北市緊急安全確保発令 北日本は大雨による災害に警戒を〈ウェザーニュースLiVEムーン・岡本結子リサ／飯島 栄一〉","date":"2025-08-20","sec":18622,"caster":"岡本 結子 リサ","weather":"飯島栄一"},{"id":"_fHGCxxVm8A","title":"【4画面ライブ】最新大雨情報／ゲリラ雷雨情報 河川氾濫や道路冠水警戒／雨雲レーダー監視　2025年8月20日(水)","date":"2025-08-20","sec":40787},{"id":"lfzXo2zaZ5o","title":"【ライブ配信終了】最新天気ニュース・地震情報 2025年8月20日(水)／秋田県仙北市に緊急安全確保発令 北日本は大雨による災害に警戒を〈ウェザーニュースLiVEイブニング・山岸愛梨／飯島栄一〉","date":"2025-08-20","sec":11349,"caster":"山岸 愛梨","weather":"飯島栄一"},{"id":"-09nLu-rDgM","title":"【ライブ配信終了】最新天気ニュース・地震情報 2025年8月20日(水)／秋田県仙北市緊急安全確保発令　北日本は大雨のおそれも＜ウェザーニュースLiVEアフタヌーン・江川清音／飯島栄一〉","date":"2025-08-20","sec":12512,"caster":"江川 清音","weather":"飯島栄一"},{"id":"3dV_ILKwoMA","title":"【ライブ配信終了】最新天気ニュース・地震情報 2025年8月20日(水)／秋田県仙北市緊急安全確保発令　北日本は大雨のおそれも〈ウェザーニュースLiVEコーヒータイム・田辺真南葉／内藤邦裕〉","date":"2025-08-20","sec":12013,"caster":"田辺 真南葉","weather":"内藤邦裕"},{"id":"0Ev57sAcH0A","title":"【ライブ配信終了】最新天気ニュース・地震情報 2025年8月20日(水)／秋田県仙北市に緊急安全確保が発令　関東以西は深刻な残暑〈ウェザーニュースLiVEサンシャイン・青原桃香／内藤邦裕〉","date":"2025-08-19","sec":12434,"caster":"青原 桃香","weather":"内藤邦裕"},{"id":"wZa93iJWpY0","title":"【ライブ配信終了】最新天気ニュース・地震情報 2025年8月20日(水)／深刻な残暑　北日本は局地的に大雨のおそれ〈ウェザーニュースLiVEモーニング・小林李衣奈／内藤邦裕〉","date":"2025-08-19","sec":13040,"caster":"小林 李衣奈","weather":"内藤邦裕"},{"id":"1A7eBOEbFMc","title":"【ライブカメラ】幕張から東京・千葉の夜景／千葉県千葉市美浜区 ウェザーニュースお天気カメラ 2025年8月19日(火)","date":"2025-08-19","sec":32904},{"id":"I5jDZ_qFMwg","title":"【ライブ】最新天気ニュース・地震情報 2025年8月20日(水) 1:00〜／深刻な残暑　北日本は局地的に大雨のおそれ〈ウェザーニュースLiVE〉","date":"2025-08-19","sec":13554},{"id":"3ttyMW6oAYE","title":"【ライブ配信終了】最新天気ニュース・地震情報 2025年8月19日(火)／あす北日本は局地的に大雨のおそれ〈ウェザーニュースLiVEムーン・岡本結子リサ／飯島栄一〉","date":"2025-08-19","sec":19155,"caster":"岡本 結子 リサ","weather":"飯島栄一"},{"id":"AfoXNW6KUxk","title":"【ライブ】最新天気ニュース・地震情報 2025年8月19日(火)／沖縄と北海道は強雨に注意〈ウェザーニュースLiVEイブニング・戸北美月／飯島栄一〉","date":"2025-08-19","sec":12503,"caster":"戸北 美月","weather":"飯島栄一"},{"id":"KjoxNG2MqeA","title":"【ライブ配信終了】最新天気ニュース・地震情報 2025年8月19日(火)／広範囲で晴れて厳しい暑さ　北海道と沖縄は強雨注意〈＜ウェザーニュースLiVEアフタヌーン・川畑玲／飯島栄一〉","date":"2025-08-19","sec":12951,"caster":"川畑 玲","weather":"飯島栄一"},{"id":"Mmh77fhyYzk","title":"【ライブ配信終了】最新天気ニュース・地震情報 2025年8月19日(火)／広範囲で晴れて厳しい暑さ　北海道と沖縄は強雨注意〈ウェザーニュースLiVEコーヒータイム・松本真央／芳野達郎〉","date":"2025-08-19","sec":11456,"caster":"松本 真央","weather":"芳野達郎"},{"id":"ulKShQONCuc","title":"【ライブカメラ】「白浜大浜ビーチ」・静岡県 下田市／2025年8月19日(火)","date":"2025-08-18","sec":42899},{"id":"tt-OVu75igc","title":"【ライブ配信終了】最新天気ニュース・地震情報 2025年8月19日(火)／広範囲で晴れて厳しい暑さ　北海道と沖縄は強雨注意〈ウェザーニュースLiVEサンシャイン・魚住茉由／芳野達郎〉","date":"2025-08-18","sec":12360,"caster":"魚住 茉由","weather":"芳野達郎"},{"id":"JzdZ-K3ircg","title":"【ライブ配信終了】最新天気ニュース・地震情報 2025年8月19日(火)／広範囲で晴れて厳しい暑さ　北海道と沖縄は強雨注意〈ウェザーニュースLiVEモーニング・青原桃香／芳野達郎〉","date":"2025-08-18","sec":12395,"caster":"青原 桃香","weather":"芳野達郎"},{"id":"EzsR-c9MrTg","title":"【ライブ】最新天気ニュース・地震情報 2025年8月19日(火)1:00〜／広範囲で晴れて厳しい暑さ 北海道と沖縄は強雨注意〈ウェザーニュースLiVE〉","date":"2025-08-18","sec":14239},{"id":"fN_6vi3-DH8","title":"【ライブカメラ】幕張から東京・千葉の夜景／千葉県千葉市美浜区 ウェザーニュースお天気カメラ 2025年8月18日(月)","date":"2025-08-18","sec":22023},{"id":"PQXSsItQ_Fg","title":"【ライブ配信終了】最新天気ニュース・地震情報 2025年8月18日(月)／明日も広範囲で晴れて厳しい暑さ〈ウェザーニュースLiVEムーン・岡本結子リサ／山口 剛央〉","date":"2025-08-18","sec":19120,"caster":"岡本 結子 リサ","weather":"山口剛央"},{"id":"wPnJ9RHQVZk","title":"【ライブ配信終了】最新天気ニュース・地震情報 2025年8月18日(月)／関東以西は天気急変に注意〈ウェザーニュースLiVEイブニング・戸北美月／山口剛央〉","date":"2025-08-18","sec":12803,"caster":"戸北 美月","weather":"山口剛央"},{"id":"is4QrTaE_jM","title":"【ライブ配信終了】最新天気ニュース・地震情報 2025年8月18日(月)／連休明けも関東以西は厳しい暑さと天気急変に注意〈＜ウェザーニュースLiVEアフタヌーン・小川千奈／山口剛央〉","date":"2025-08-18","sec":12655,"caster":"小川 千奈","weather":"山口剛央"},{"id":"1QBYYQ8hx8M","title":"【ライブ配信終了】最新天気ニュース・地震情報 2025年8月18日(月)／連休明けも関東以西は厳しい暑さと天気急変に注意〈ウェザーニュースLiVEコーヒータイム・松本真央／芳野達郎〉","date":"2025-08-18","sec":12479,"caster":"松本 真央","weather":"芳野達郎"},{"id":"Cny9lzqE3A0","title":"【ライブカメラ】「白浜大浜ビーチ」連休明けも暑さに負けず頑張りましょう！・静岡県 下田市／2025年8月18日(月)","date":"2025-08-17","sec":42899},{"id":"IKUwOohujSI","title":"【ライブ配信終了】最新天気ニュース・地震情報 2025年8月18日(月)／連休明けも関東以西は厳しい暑さと天気急変に注意〈ウェザーニュースLiVEサンシャイン・小林李衣奈／芳野達郎〉","date":"2025-08-17","sec":12151,"caster":"小林 李衣奈","weather":"芳野達郎"},{"id":"nmkuLMZybKc","title":"【ライブ配信終了】最新天気ニュース・地震情報 2025年8月18日(月)／連休明けも関東以西は暑さと天気急変に注意〈ウェザーニュースLiVEモーニング・青原桃香／芳野達郎〉","date":"2025-08-17","sec":12666,"caster":"青原 桃香","weather":"芳野達郎"},{"id":"o_9nCJL5BBE","title":"【ライブ】最新天気ニュース・地震情報 2025年8月18日(月) 1:00〜／厳しい暑さと天気急変に注意〈ウェザーニュースLiVE〉","date":"2025-08-17","sec":13653},{"id":"4RpeXHVJVaA","title":"【ライブ配信終了】最新天気ニュース・地震情報 2025年8月17日(日)20:00〜／お盆休み明け、しばらく猛暑に〈ウェザーニュースLiVEムーン・駒木 結衣／森田 清輝〉","date":"2025-08-17","sec":19260,"caster":"駒木 結衣","weather":"森田清輝"},{"id":"2JsEffBwNbM","title":"【ライブカメラ】お盆休み最終日「白浜大浜ビーチ」静岡県 下田市/2025年8月17日(日)","date":"2025-08-17","sec":36146},{"id":"jgdK_rzOrwY","title":"【ライブ配信終了】最新天気ニュース・地震情報 2025年8月17日(日)／東北では一時的な激しい雷雨に警戒〈ウェザーニュースLiVEイブニング・小川 千奈／森田 清輝〉","date":"2025-08-17","sec":11459,"caster":"小川 千奈","weather":"森田清輝"},{"id":"bIA9A6bbBls","title":"【ライブ配信終了】最新天気ニュース・地震情報 2025年8月17日(日)／西日本、東日本で厳しい残暑〈＜ウェザーニュースLiVEアフタヌーン・松本真央／森田清輝〉","date":"2025-08-17","sec":11479,"caster":"松本 真央","weather":"森田清輝"},{"id":"x0yGbJMHmwA","title":"【ライブ配信終了】最新天気ニュース・地震情報 2025年8月17日(日)／西日本、東日本で厳しい残暑〈ウェザーニュースLiVEコーヒータイム・小林李衣奈／山口剛央〉","date":"2025-08-17","sec":12835,"caster":"小林 李衣奈","weather":"山口剛央"},{"id":"xTSF-uYNuGM","title":"【ライブ配信終了】最新天気ニュース・地震情報 2025年8月17日(日)／西日本、東日本で厳しい残暑〈ウェザーニュースLiVEサンシャイン・魚住茉由 ／山口剛央〉","date":"2025-08-16","sec":12343,"caster":"魚住 茉由","weather":"山口剛央"},{"id":"KfWr2GNVtyo","title":"【ライブ配信終了】日向灘でM5.8の地震／最新天気ニュース・地震情報 2025年8月17日(日)／西日本、東日本で厳しい残暑〈ウェザーニュースLiVEモーニング・田辺真南葉／山口剛央〉","date":"2025-08-16","sec":12149,"caster":"田辺 真南葉","weather":"山口剛央"},{"id":"C7VJYWqE-2M","title":"【ライブ配信終了】最新天気ニュース・地震情報 2025年8月17日(日)1:00〜／西日本、東日本で厳しい残暑〈ウェザーニュースLiVE〉","date":"2025-08-16","sec":13806},{"id":"OzuOAddvNP4","title":"【ライブ配信終了】最新天気ニュース・地震情報 2025年8月16日(土)／明日は北日本で雨具の出番に〈ウェザーニュースLiVEムーン・戸北 美月／森田 清輝〉","date":"2025-08-16","sec":18608,"caster":"戸北 美月","weather":"森田清輝"},{"id":"vwapfK5egJM","title":"【4K＆高音質】\"感動日本一\"の夜空をあなたへ | 第32回赤川花火大会 2025（2025.8.16 19:20〜）","date":"2025-08-16","sec":7856},{"id":"4yMMCgCaJkw","title":"【ウェザーニュースキャスター山岸愛梨と見る・涼む】\"感動日本一\"の夜空をあなたへ | 第32回赤川花火大会 2025（2025.8.16 19:20〜）","date":"2025-08-16","sec":6902,"caster":"山岸 愛梨"},{"id":"7gV36uj4n2k","title":"【ライブ配信終了】最新天気ニュース・地震情報 2025年8月16日(土)／関東以西で雨雲発達　埼玉・静岡で猛烈な雨に〈ウェザーニュースLiVEイブニング・岡本結子リサ／森田 清輝〉","date":"2025-08-16","sec":11846,"caster":"岡本 結子 リサ","weather":"森田清輝"},{"id":"J-TuXjoeIPU","title":"【ライブ配信終了】最新天気ニュース・地震情報 2025年8月16日(土)／関東以西で雨雲発達　埼玉・静岡で猛烈な雨に〈＜ウェザーニュースLiVEアフタヌーン・小川千奈／森田清輝〉","date":"2025-08-16","sec":12785,"caster":"小川 千奈","weather":"森田清輝"},{"id":"yjP2TdPUdOc","title":"【ライブ配信終了】最新天気ニュース・地震情報 2025年8月16日(土)／西日本は晴れて厳しい暑さ　関東は午前中から雨の所も〈ウェザーニュースLiVEコーヒータイム・小林李衣奈／山口剛央〉","date":"2025-08-16","sec":12405,"caster":"小林 李衣奈","weather":"山口剛央"},{"id":"D_P6lGjYaZI","title":"【ライブカメラ】お盆休み「白浜大浜ビーチ」静岡県 下田市/2025年8月16日(土)","date":"2025-08-15","sec":42899},{"id":"taTEHkD3lAk","title":"【ライブ配信終了】最新天気ニュース・地震情報 2025年8月16日(土)／西日本は晴れて厳しい暑さ　関東は午前中から雨の所も〈ウェザーニュースLiVEサンシャイン・田辺真南葉 ／山口剛央〉","date":"2025-08-15","sec":12347,"caster":"田辺 真南葉","weather":"山口剛央"},{"id":"_I0AC9IGcAs","title":"【ライブ配信終了】最新天気ニュース・地震情報 2025年8月16日(土)／西日本は晴れて厳しい暑さ　関東は午前中から雨の所も〈ウェザーニュースLiVEモーニング・青原桃香／山口剛央〉","date":"2025-08-15","sec":11496,"caster":"青原 桃香","weather":"山口剛央"},{"id":"LYAp7ay3MGA","title":"【ライブカメラ】幕張から東京・千葉の夜景／千葉県千葉市美浜区 ウェザーニュースお天気カメラ 2025年8月15日(金)","date":"2025-08-15","sec":24215},{"id":"9AjFNDlt808","title":"【ライブ】最新天気ニュース・地震情報 2025年8月16日(土) 1:00〜／西日本は晴れて厳しい暑さ　関東は午前中から雨の所も〈ウェザーニュースLiVE〉","date":"2025-08-15","sec":14557},{"id":"TZBQ6uR0-Kc","title":"【ライブ配信終了】最新天気ニュース・地震情報 2025年8月15日(木)21:00〜／お盆休み終盤は関東以西で猛暑〈ウェザーニュースLiVEムーン・駒木結衣／宇野沢達也〉","date":"2025-08-15","sec":11998,"caster":"駒木 結衣","weather":"宇野沢達也"},{"id":"_OfT5DII53I","title":"【JR東日本×ウェザーニュース】避暑旅タイアップ特別企画　第9回出演：駒木結衣","date":"2025-08-15","sec":2394,"caster":"駒木 結衣"},{"id":"Slt5PbBzLrs","title":"【4K LIVE】第77回諏訪湖祭湖上花火大会｜天然の音響劇場が生む「轟」と湖上の芸術「煌めき」を体感せよ（2025.8.15 19:00~）＜メイン＞","date":"2025-08-15","sec":8185},{"id":"CZJkERyDzRY","title":"【4K LIVE】第77回諏訪湖祭湖上花火大会｜天然の音響劇場が生む「轟」と湖上の芸術「煌めき」を体感せよ（2025.8.15 19:00~）＜引き固定＞","date":"2025-08-15","sec":7315},{"id":"-tlwPwCZuYA","title":"【ライブ】最新天気ニュース・地震情報 2025年8月15日(金)／お盆休み終盤は関東以西で猛暑〈ウェザーニュースLiVEムーン・駒木 結衣／宇野沢 達也〉","date":"2025-08-15","sec":4383,"caster":"駒木 結衣","weather":"宇野沢達也"},{"id":"5m3g9dC7pWE","title":"【ライブ配信終了】最新天気ニュース・地震情報 2025年8月15日(金)／お盆休み終盤は東・西日本で猛暑とゲリラ雷雨に注意〈ウェザーニュースLiVEイブニング・岡本結子リサ／宇野沢達也〉","date":"2025-08-15","sec":11695,"caster":"岡本 結子 リサ","weather":"宇野沢達也"},{"id":"x-Z60SE9bEI","title":"【ライブ配信終了】最新天気ニュース・地震情報 2025年8月15日(金)／お盆休み終盤は関東以西で猛暑〈＜ウェザーニュースLiVEアフタヌーン・白井ゆかり／宇野沢達也〉","date":"2025-08-15","sec":12273,"caster":"白井 ゆかり","weather":"宇野沢達也"},{"id":"kIp3bM4DCNc","title":"【ライブ配信終了】最新天気ニュース・地震情報 2025年8月15日(金)／お盆休み終盤は関東以西で猛暑〈ウェザーニュースLiVEコーヒータイム・魚住茉由／山口剛央〉","date":"2025-08-15","sec":12709,"caster":"魚住 茉由","weather":"山口剛央"},{"id":"ZYt5_W8bOpQ","title":"【気候変動番組】100年天気予報~伝統が続けられない？気候変動が奪う“夏の風物詩”~/2025年8月15日(金)12:00~/魚住茉由・吉良真由子","date":"2025-08-15","sec":2091,"caster":"魚住 茉由"},{"id":"qY-swVCFgyo","title":"【ライブカメラ】お盆休み「白浜大浜ビーチ」静岡県 下田市/2025年8月15日(金)","date":"2025-08-14","sec":42900},{"id":"hxmktmSEBcg","title":"【ライブ配信終了】最新天気ニュース・地震情報 2025年8月15日(金)／お盆休み終盤は関東以西で猛暑〈ウェザーニュースLiVEサンシャイン・松本真央 ／山口剛央〉","date":"2025-08-14","sec":12377,"caster":"松本 真央","weather":"山口剛央"},{"id":"aP8S-3ytyxI","title":"【ライブ配信終了】最新天気ニュース・地震情報 2025年8月15日(金)／お盆休み終盤は関東以西で猛暑〈ウェザーニュースLiVEモーニング・青原桃香／山口剛央〉","date":"2025-08-14","sec":12343,"caster":"青原 桃香","weather":"山口剛央"},{"id":"k5b1YBuLYj8","title":"【ライブ配信終了】最新天気ニュース・地震情報 2025年8月15日(金)1:00〜／お盆休み終盤は関東以西で猛暑〈ウェザーニュースLiVE〉","date":"2025-08-14","sec":16033},{"id":"n_RKWIc1az8","title":"【ライブカメラ】幕張から東京・千葉の夜景／千葉県千葉市美浜区 ウェザーニュースお天気カメラ 2025年8月14日(木)","date":"2025-08-14","sec":27157},{"id":"VC-3w8BLH9s","title":"【ライブ配信終了】最新天気ニュース・地震情報 2025年8月14日(木)／〈ウェザーニュースLiVEムーン・駒木結衣／本田竜也〉","date":"2025-08-14","sec":17253,"caster":"駒木 結衣","weather":"本田竜也"},{"id":"1G-skdWnj00","title":"【ライブ配信終了】最新天気ニュース・地震情報 2025年8月14日(木)／西日本はゲリラ雷雨、東日本・北日本はにわか雨に注意〈ウェザーニュースLiVEイブニング・戸北美月／本田竜也〉","date":"2025-08-14","sec":12505,"caster":"戸北 美月","weather":"本田竜也"},{"id":"g9dxypX4rCQ","title":"【ライブ配信終了】最新天気ニュース・地震情報 2025年8月14日(木)／西日本はゲリラ雷雨、東日本・北日本はにわか雨に注意〈＜ウェザーニュースLiVEアフタヌーン・白井ゆかり／本田竜也〉","date":"2025-08-14","sec":12442,"caster":"白井 ゆかり","weather":"本田竜也"},{"id":"AHXeG0wrCTY","title":"【ライブ配信終了】最新天気ニュース・地震情報 2025年8月14日(木)／西日本はゲリラ雷雨、東日本・北日本はにわか雨に注意〈ウェザーニュースLiVEコーヒータイム・田辺真南葉／山口剛央〉","date":"2025-08-14","sec":12556,"caster":"田辺 真南葉","weather":"山口剛央"},{"id":"Y_JsRg9x9qA","title":"【ライブカメラ】お盆休み「白浜大浜ビーチ」静岡県 下田市/2025年8月14日(木)","date":"2025-08-13","sec":42900},{"id":"IWTL60YdNzQ","title":"【ライブ配信終了】最新天気ニュース・地震情報 2025年8月14日(木)／西日本はゲリラ雷雨、東日本・北日本はにわか雨に注意〈ウェザーニュースLiVEサンシャイン・青原桃香／山口剛央〉","date":"2025-08-13","sec":12521,"caster":"青原 桃香","weather":"山口剛央"},{"id":"tfYthN4pcok","title":"【ライブ配信終了】最新天気ニュース・地震情報 2025年8月14日(水)／茨城県沖M5.1の地震　西日本は晴れても天気急変に注意〈ウェザーニュースLiVEモーニング・福吉貴文／山口剛央〉","date":"2025-08-13","sec":12272,"caster":"福吉 貴文","weather":"山口剛央"},{"id":"kA8e1dKUois","title":"【ライブ配信終了】最新天気ニュース・地震情報 2025年8月13日(水)23:00〜／西日本は晴れても天気急変注意　東日本や北日本は雲優勢〈ウェザーニュースLiVE〉","date":"2025-08-13","sec":20573},{"id":"x9ro14QFx_I","title":"【ライブカメラ】幕張から東京・千葉の夜景／千葉県千葉市美浜区 ウェザーニュースお天気カメラ 2025年8月13日(水)","date":"2025-08-13","sec":28683},{"id":"T3z3gMuzi5s","title":"【天体ライブ】ペルセウス座流星群2025 三大流星群の一つが見頃に／北海道なよろ市立天文台きたすばるより 2025年8月13日(水) Perseid meteor shower 2025","date":"2025-08-13","sec":31824},{"id":"OHqXubVKeU0","title":"【天体ライブ】ペルセウス座流星群2025 三大流星群の一つが見頃に／出演：山岸愛梨（星空案内人）2025年8月13日(水)22:00〜 Perseid meteor shower 2025","date":"2025-08-13","sec":4171,"caster":"山岸 愛梨"},{"id":"AlDdAb4iYIU","title":"【ライブ配信終了】最新天気ニュース・地震情報 2025年8月13日(水)／あす西日本は晴れても天気急変注意　東日本や北日本は雲優勢〈ウェザーニュースLiVEムーン・山岸 愛梨／飯島 栄一〉","date":"2025-08-13","sec":3871,"caster":"山岸 愛梨","weather":"飯島栄一"},{"id":"uka4OnvkZUw","title":"目指せ1000の『なるほどの〜！』 気象で読み解く\"感動日本一\"赤川花火の秘密 〜鶴岡の歴史・自然・食文化〜（2025.8.13 20:00〜）","date":"2025-08-13","sec":4673},{"id":"bmkHzp7jKv8","title":"【ライブ】最新天気ニュース・地震情報 2025年8月13日(水)／天気回復　厳しい暑さに要注意〈ウェザーニュースLiVEイブニング・岡本結子リサ／飯島 栄一〉","date":"2025-08-13","sec":11431,"caster":"岡本 結子 リサ","weather":"飯島栄一"},{"id":"Q7LiwxLD-B0","title":"【ライブ配信終了】最新天気ニュース・地震情報 2025年8月13日(水)／天気回復　厳しい暑さに要注意＜ウェザーニュースLiVEアフタヌーン・駒木結衣／飯島栄一〉","date":"2025-08-13","sec":11826,"caster":"駒木 結衣","weather":"飯島栄一"},{"id":"xy9R9eQpaKM","title":"【ライブ配信終了】最新天気ニュース・地震情報 2025年8月13日(水)／天気回復　厳しい暑さに要注意〈ウェザーニュースLiVEコーヒータイム・魚住茉由／芳野達郎〉","date":"2025-08-13","sec":12677,"caster":"魚住 茉由","weather":"芳野達郎"},{"id":"JvdMW5a5rtg","title":"【ライブ配信終了】最新天気ニュース・地震情報 2025年8月13日(水)／天気回復　厳しい暑さに要注意〈ウェザーニュースLiVEサンシャイン・青原桃香 ／芳野達郎〉","date":"2025-08-12","sec":12571,"caster":"青原 桃香","weather":"芳野達郎"},{"id":"cnQksShzP9I","title":"【ライブ配信終了】最新天気ニュース・地震情報 2025年8月13日(水)／天気回復 厳しい暑さに要注意〈ウェザーニュースLiVEモーニング・福吉貴文／芳野達郎〉","date":"2025-08-12","sec":12457,"caster":"福吉 貴文","weather":"芳野達郎"},{"id":"lmUlVG3w1JI","title":"【ライブ配信終了】最新天気ニュース・地震情報 2025年8月13日(水)1:00〜／天気回復　厳しい暑さに要注意〈ウェザーニュースLiVE〉","date":"2025-08-12","sec":19799},{"id":"vcCOFG49qWU","title":"【天体ライブ】ペルセウス座流星群2025 三大流星群の一つがピーク／沖縄県・名護市より 2025年8月12日(火) Perseid meteor shower 2025","date":"2025-08-12","sec":21135},{"id":"9f3WE12uCuk","title":"【天体ライブ】ペルセウス座流星群2025 三大流星群の一つがピーク／北海道なよろ市立天文台きたすばるより 2025年8月12日(火) Perseid meteor shower 2025","date":"2025-08-12","sec":15955},{"id":"arwRpbOvYKo","title":"【天体ライブ】ペルセウス座流星群2025 三大流星群の一つがピーク／田辺真南葉キャスター初流星中継 2025年8月12日(火)20:30〜 Perseid meteor shower 2025","date":"2025-08-12","sec":14570,"caster":"田辺 真南葉"},{"id":"7VlpO-N3IBQ","title":"【天体ライブ】ペルセウス座流星群2025 三大流星群の一つがピーク／松本真央キャスター初流星中継 2025年8月12日(火)20:30〜 Perseid meteor shower 2025","date":"2025-08-12","sec":12870,"caster":"松本 真央"},{"id":"56uygLj6FDU","title":"【天体ライブ】ペルセウス座流星群2025 三大流星群の一つがピーク／出演：山岸愛梨・平松正顕（国立天文台）2025年8月12日(火)21:00〜 Perseid meteor shower 2025","date":"2025-08-12","sec":8311,"caster":"山岸 愛梨"},{"id":"jwVgX8YRs_A","title":"【4画面 雨雲レーダーライブ】各地で強雨注意 大雨峠越えても土砂災害など警戒／雨雲レーダー監視　2025年8月12日(火)","date":"2025-08-12","sec":37858},{"id":"r-xCwG1el8M","title":"【ライブ配信終了】最新天気ニュース・地震情報 2025年8月12日(火)／局地的に雨が強まる引き続き災害発生に警戒を〈ウェザーニュースLiVEムーン・戸北 美月／飯島 栄一〉","date":"2025-08-12","sec":4560,"caster":"戸北 美月","weather":"飯島栄一"},{"id":"95vYzuMECyg","title":"【ライブ配信終了】最新天気ニュース・地震情報 2025年8月12日(火)／西日本や北陸など日本海側は強雨警戒〈ウェザーニュースLiVEイブニング・岡本結子リサ／飯島 栄一〉","date":"2025-08-12","sec":11781,"caster":"岡本 結子 リサ","weather":"飯島栄一"},{"id":"-8km2C_loZU","title":"【ライブ配信終了】最新天気ニュース・地震情報 2025年8月12日(火)／連休明け 北陸など日本海側は強雨警戒〈ウェザーニュースLiVEアフタヌーン・魚住茉由／飯島栄一〉","date":"2025-08-12","sec":12824,"caster":"魚住 茉由","weather":"飯島栄一"},{"id":"rmQUU3TKJVw","title":"【ライブ配信終了】最新天気ニュース・地震情報 2025年8月12日(火)／連休明け 北陸など日本海側は強雨警戒〈ウェザーニュースLiVEコーヒータイム・小林李衣奈／内藤邦裕〉","date":"2025-08-12","sec":12425,"caster":"小林 李衣奈","weather":"内藤邦裕"},{"id":"SDLC9d3Fe54","title":"【ライブ配信終了】最新天気ニュース・地震情報 2025年8月12日(火)／連休明け 北陸など日本海側は強雨警戒〈ウェザーニュースLiVEサンシャイン・福吉貴文 ／内藤邦裕〉","date":"2025-08-11","sec":12025,"caster":"福吉 貴文","weather":"内藤邦裕"},{"id":"INsaNn1t66c","title":"【ライブ配信終了】最新天気ニュース・地震情報 2025年8月12日(火)／北陸など日本海側は強雨警戒〈ウェザーニュースLiVEモーニング・小川千奈／内藤邦裕〉","date":"2025-08-11","sec":12342,"caster":"小川 千奈","weather":"内藤邦裕"},{"id":"nHPqlXIvBvI","title":"【ライブ配信終了】最新天気ニュース・地震情報 2025年8月12日(火)1:00〜／北陸など日本海側は強雨警戒〈ウェザーニュースLiVE〉","date":"2025-08-11","sec":13455},{"id":"DaMxrf9X_ac","title":"【ライブ配信終了】最新天気ニュース・地震情報 2025年8月11日(月)／記録的な大雨による災害発生に警戒を〈ウェザーニュースLiVEムーン・山岸 愛梨／山口剛央〉","date":"2025-08-11","sec":19003,"caster":"山岸 愛梨","weather":"山口剛央"},{"id":"rpTJohq8K7g","title":"【ライブ配信終了】最新天気ニュース・地震情報 2025年8月11日(月)／記録的な大雨による災害の発生に警戒を〈ウェザーニュースLiVEイブニング・戸北 美月／山口 剛央〉","date":"2025-08-11","sec":10543,"caster":"戸北 美月","weather":"山口剛央"},{"id":"seAo-zHvDzE","title":"【ライブ配信終了】最新天気ニュース・地震情報 2025年8月11日(月)／線状降水帯による豪雨〈ウェザーニュースLiVEアフタヌーン・魚住茉由／山口剛央〉","date":"2025-08-11","sec":12318,"caster":"魚住 茉由","weather":"山口剛央"},{"id":"dJIBz-hd97c","title":"【ライブ配信終了】最新天気ニュース・地震情報 2025年8月11日(月)／熊本県では大雨特別警報拡大〈ウェザーニュースLiVEコーヒータイム・小林李衣奈／内藤邦裕〉","date":"2025-08-11","sec":12183,"caster":"小林 李衣奈","weather":"内藤邦裕"},{"id":"_Ydd80rkBUY","title":"【ライブ配信終了】最新天気ニュース・地震情報 2025年8月11日(月)／熊本県に#大雨特別警報・#線状降水帯 による豪雨 #緊急安全確保〈ウェザーニュースLiVEサンシャイン・福吉貴文 ／内藤邦裕〉","date":"2025-08-10","sec":12351,"caster":"福吉 貴文","weather":"内藤邦裕"},{"id":"OtIbXXZLj7Y","title":"【ライブ配信終了】最新天気ニュース・地震情報 2025年8月11日(月)／熊本県に大雨特別警報・線状降水帯による豪雨〈ウェザーニュースLiVEモーニング・小川千奈／内藤邦裕〉","date":"2025-08-10","sec":12188,"caster":"小川 千奈","weather":"内藤邦裕"},{"id":"4pe2ycb_-Ao","title":"【大雨ライブ】福岡県・山口県で線状降水帯による大雨 災害発生に厳重警戒 2025年8月10日(日)","date":"2025-08-10","sec":42901},{"id":"bBvx87lJO8U","title":"【ライブ配信終了】線状降水帯による大雨に警戒・大雨特別警報 2025年8月11日(月)1:00〜／最新天気ニュース・地震情報〈ウェザーニュースLiVE〉","date":"2025-08-10","sec":13671},{"id":"itWaifJuszk","title":"【ライブ配信終了】最新天気ニュース・地震情報 2025年8月10日(日)／線状降水帯による大雨に警戒〈ウェザーニュースLiVEムーン・山岸 愛梨／森田 清輝〉","date":"2025-08-10","sec":18182,"caster":"山岸 愛梨","weather":"森田清輝"},{"id":"AKRShTAIbQg","title":"【ライブ配信終了】最新天気ニュース・地震情報 2025年8月10日(日)／九州や中国地方は線状降水帯による大雨　災害発生に厳重警戒〈ウェザーニュースLiVEイブニング・岡本結子リサ／森田清輝〉","date":"2025-08-10","sec":10783,"caster":"岡本 結子 リサ","weather":"森田清輝"},{"id":"JpIYTaT77Ns","title":"【ライブ配信終了】最新天気ニュース・地震情報 2025年8月10日(日)／九州や中国地方は線状降水帯による大雨　災害発生に厳重警戒〈ウェザーニュースLiVEアフタヌーン・小林李衣奈／森田清輝〉","date":"2025-08-10","sec":12444,"caster":"小林 李衣奈","weather":"森田清輝"},{"id":"0hmWImxdSok","title":"【ライブ配信終了】最新天気ニュース・地震情報 2025年8月10日(日)／三連休中日は広範囲で本降りの雨 九州や中国地方は大雨に厳重警戒〈ウェザーニュースLiVEコーヒータイム・松本真央／山口剛央〉","date":"2025-08-10","sec":11415,"caster":"松本 真央","weather":"山口剛央"},{"id":"CFSIhbU199s","title":"【4画面 雨雲レーダーライブ配信終了】三連休中日は広範囲で本降りの雨　九州北部～中国西部は大雨に厳重警戒／雨雲レーダー監視　2025年8月10日(日)","date":"2025-08-09","sec":41508},{"id":"jjoVX9WtG4o","title":"【ライブ配信終了】最新天気ニュース・地震情報 2025年8月10日(日)／三連休中日は広範囲で本降りの雨 九州北部～中国西部は大雨に厳重警戒","date":"2025-08-09","sec":12696},{"id":"tsi3LVoT2H4","title":"【ライブ配信終了】最新天気ニュース・地震情報 2025年8月10日(日)／三連休中日は広範囲で本降りの雨　九州北部～中国西部は大雨に厳重警戒〈ウェザーニュースLiVEモーニング・青原桃香／山口剛央〉","date":"2025-08-09","sec":11185,"caster":"青原 桃香","weather":"山口剛央"},{"id":"1gphzVpSrlE","title":"【ライブ配信終了】最新天気ニュース・地震情報 2025年8月10日(日)1:00〜／福岡県では線状降水帯による大雨〈ウェザーニュースLiVE〉","date":"2025-08-09","sec":14111},{"id":"o_M1tGNwNWI","title":"【ライブカメラ】北九州市各地のソラカメ／九州・中国地方で線状降水帯による大雨のおそれ　2025年8月10日(日)","date":"2025-08-09","sec":9235},{"id":"_7y_rJLON64","title":"【天体ライブ】満月ライブカメラ スタージョンムーン・チョウザメ月／福島県・星の村天文台 2025年8月9日(土) ウェザーニュースLiVE","date":"2025-08-09","sec":15660},{"id":"-oNcuj9t-6U","title":"【4画面 雨雲レーダーライブ】三連休初日は九州で大雨警戒／雨雲レーダー監視　2025年8月9日(土)","date":"2025-08-09","sec":26536},{"id":"hQ5UX75or-c","title":"【ライブ配信終了】最新天気ニュース・地震情報 2025年8月9日(土)／明日は九州北部から中国西部で災害級の大雨に警戒〈ウェザーニュースLiVEムーン・岡本 結子リサ／森田 清輝〉","date":"2025-08-09","sec":18663,"caster":"岡本 結子 リサ","weather":"森田清輝"},{"id":"jvalGy0NvMM","title":"【天体ライブ】満月ライブカメラ スタージョンムーン・チョウザメ月／千葉県・幕張 2025年8月9日(土) ウェザーニュースLiVE","date":"2025-08-09","sec":16296},{"id":"BYE8xEH7_Wg","title":"【天体ライブ】満月ライブカメラ スタージョンムーン・チョウザメ月／北海道・なよろ市立天文台きたすばる 2025年8月9日(土) ウェザーニュースLiVE","date":"2025-08-09","sec":12577},{"id":"RsByRjDvW0w","title":"【ライブ配信終了】最新天気ニュース・地震情報 2025年8月9日(土)／明日は九州北部から中国西部で災害級の大雨に警戒　線状降水帯のおそれも〈ウェザーニュースLiVEイブニング・戸北美月／森田清輝〉","date":"2025-08-09","sec":11354,"caster":"戸北 美月","weather":"森田清輝"},{"id":"xISbpNZah8Y","title":"【ライブ配信終了】最新天気ニュース・地震情報 2025年8月9日(土)／三連休初日は九州で大雨警戒　関東や東海は晴れて暑い〈ウェザーニュースLiVEアフタヌーン・魚住茉由／森田清輝〉","date":"2025-08-09","sec":11442,"caster":"魚住 茉由","weather":"森田清輝"},{"id":"nFprixHDqBI","title":"【ライブ配信終了】最新天気ニュース・地震情報 2025年8月9日(土)／三連休初日は九州で大雨警戒〈ウェザーニュースLiVEコーヒータイム・松本真央／山口剛央〉","date":"2025-08-09","sec":11510,"caster":"松本 真央","weather":"山口剛央"},{"id":"CtTTvikZU90","title":"【4画面 雨雲レーダーライブ】三連休初日は九州で大雨警戒／雨雲レーダー監視　2025年8月9日(土)","date":"2025-08-08","sec":42899},{"id":"7xPYRZqv31w","title":"【ライブ配信終了】最新天気ニュース・地震情報 2025年8月9日(土)／三連休初日は九州で大雨警戒　関東や東海は晴れて暑い〈ウェザーニュースLiVEサンシャイン・田辺真南葉／山口剛央〉","date":"2025-08-08","sec":12299,"caster":"田辺 真南葉","weather":"山口剛央"},{"id":"roVmcoTVTLw","title":"【ライブ配信終了】最新天気ニュース・地震情報 2025年8月9日(土)／三連休初日は九州で大雨警戒　関東や東海は晴れて暑い〈ウェザーニュースLiVEモーニング・小川千奈／山口剛央〉","date":"2025-08-08","sec":12508,"caster":"小川 千奈","weather":"山口剛央"},{"id":"MvCD-JInRYc","title":"【ライブ配信終了】秋田県由利本荘市に緊急安全確保・三連休は西日本で大雨のおそれ／気象情報・地震情報 2025年8月9日(土)1:00〜〈ウェザーニュースLiVE〉","date":"2025-08-08","sec":14263},{"id":"DTGUtdAzv4k","title":"【4画面 雨雲レーダーライブ】各地でゲリラ雷雨のおそれ／落雷や突風、ひょうなどに注意／大気の状態が不安定／雨雲レーダー監視　2025年8月8日(金)","date":"2025-08-08","sec":42900},{"id":"jxdjD2rf0MU","title":"【ライブ配信終了】秋田県に緊急安全確保／土砂災害に警戒 2025年8月8日(金)〈ウェザーニュースLiVEムーン・駒木 結衣／宇野沢 達也〉","date":"2025-08-08","sec":18667,"caster":"駒木 結衣","weather":"宇野沢達也"},{"id":"MsJQsZHJQ3U","title":"【ライブ配信終了】最新天気ニュース・地震情報 2025年8月8日(金)／九州は大雨災害に警戒を その他のエリアも雨具の用意を〈ウェザーニュースLiVEイブニング・山岸愛梨／宇野沢達也〉","date":"2025-08-08","sec":12394,"caster":"山岸 愛梨","weather":"宇野沢達也"},{"id":"guJiA8WeNyM","title":"【ライブ配信終了】最新天気ニュース・地震情報 2025年8月8日(金)鹿児島県の大雨特別警報は大雨警報に／関東など各地で雷雨やひょうに警戒〈ウェザーニュースLiVEアフタヌーン・江川清音／宇野沢達也〉","date":"2025-08-08","sec":11876,"caster":"江川 清音","weather":"宇野沢達也"},{"id":"4hWbg6-ge78","title":"【ライブ配信終了】最新天気ニュース・地震情報 2025年8月8日(金)／鹿児島県に大雨特別警報発表　大雨災害発生に厳重警戒〈ウェザーニュースLiVEコーヒータイム・青原桃香／山口剛央〉","date":"2025-08-08","sec":12032,"caster":"青原 桃香","weather":"山口剛央"},{"id":"7TX1sYaQjbo","title":"【4画面ライブ】鹿児島県の大雨特別警報は大雨警報へ／薩摩地方では線状降水帯による大雨も／災害発生に警戒/最新大雨情報／2025年8月8日(金)","date":"2025-08-07","sec":36365},{"id":"9YVx1RWsf0s","title":"【ライブ配信終了】最新天気ニュース・地震情報 2025年8月8日(金)／鹿児島県に大雨特別警報発表　大雨災害発生に厳重警戒〈ウェザーニュースLiVEサンシャイン・小川千奈／山口剛央〉","date":"2025-08-07","sec":12157,"caster":"小川 千奈","weather":"山口剛央"},{"id":"WE47BINnINo","title":"【ライブ配信終了】鹿児島県に大雨特別警報発表　大雨災害発生に厳重警戒/最新天気ニュース・地震情報 2025年8月8日(金)〈ウェザーニュースLiVEモーニング・福吉貴文／山口剛央〉","date":"2025-08-07","sec":13120,"caster":"福吉 貴文","weather":"山口剛央"},{"id":"qr1ZMZDC1-8","title":"【ライブ配信終了】鹿児島県（奄美地方を除く）で線状降水帯による大雨/最新天気ニュース・地震情報 2025年8月8日(金)1:00〜〈ウェザーニュースLiVE〉","date":"2025-08-07","sec":14174},{"id":"ohBSHT2xGlk","title":"【ライブ配信終了】最新天気ニュース・地震情報 2025年8月7日(木)／九州は明日も激しい雨に警戒〈ウェザーニュースLiVEムーン・岡本結子リサ／本田 竜也〉","date":"2025-08-07","sec":19146,"caster":"岡本 結子 リサ","weather":"本田竜也"},{"id":"TwaviUXf_IY","title":"【4K＆高音質】第37回 神明の花火 生中継（2025.8.7）／ 山梨県最大級2万発をライブ配信＜メイン＞","date":"2025-08-07","sec":5911},{"id":"oUuv8018LV4","title":"【4K＆高音質】第37回 神明の花火 生中継（2025.8.7）／ 山梨県最大級2万発をライブ配信＜引き固定＞","date":"2025-08-07","sec":5006},{"id":"FmooZGQSY7Q","title":"【ライブ配信終了】最新天気ニュース・地震情報 2025年8月7日(木)／九州は明日も激しい雨に警戒〈ウェザーニュースLiVEイブニング・駒木結衣／本田竜也〉","date":"2025-08-07","sec":12466,"caster":"駒木 結衣","weather":"本田竜也"},{"id":"EeDk5d4nECc","title":"【ライブ配信終了】最新天気ニュース・地震情報 2025年8月7日(木)北陸や東北日本海側は荒天警戒〈ウェザーニュースLiVEアフタヌーン・松本真央／本田竜也〉","date":"2025-08-07","sec":11567,"caster":"松本 真央","weather":"本田竜也"},{"id":"BUWiWO_E0v4","title":"【ライブ配信終了】最新天気ニュース・地震情報 2025年8月7日(木)／北陸や東北日本海側は荒天警戒　線状降水帯発生も〈ウェザーニュースLiVEコーヒータイム・青原桃香／芳野達郎〉","date":"2025-08-07","sec":12055,"caster":"青原 桃香","weather":"芳野達郎"},{"id":"MLquRqyEmQ8","title":"【ライブ配信終了】最新天気ニュース・地震情報 2025年8月7日(木)／北陸や東北日本海側は大雨に警戒〈ウェザーニュースLiVEサンシャイン・小川千奈／芳野達郎〉","date":"2025-08-06","sec":12608,"caster":"小川 千奈","weather":"芳野達郎"},{"id":"lSqfWzSNiB4","title":"【ライブ配信終了】最新天気ニュース・地震情報 2025年8月7日(木)／北陸や東北日本海側は大雨に警戒〈ウェザーニュースLiVEモーニング・福吉貴文／芳野達郎〉","date":"2025-08-06","sec":12549,"caster":"福吉 貴文","weather":"芳野達郎"},{"id":"ZakGdCM_1Ig","title":"【ライブ配信終了】最新天気ニュース・地震情報 2025年8月7日(木)1:00〜／北陸や東北日本海側は大雨に警戒〈ウェザーニュースLiVE〉","date":"2025-08-06","sec":14511},{"id":"Hx9cwASsbWc","title":"【ライブ配信終了】最新天気ニュース・地震情報 2025年8月6日(水)／明日にかけて北陸～東北日本海側は大雨警戒〈ウェザーニュースLiVEムーン・岡本 結子リサ／宇野沢 達也〉","date":"2025-08-06","sec":18705,"caster":"岡本 結子 リサ","weather":"宇野沢達也"},{"id":"CT4knLooFhs","title":"【ライブ配信終了】最新天気ニュース・地震情報 2025年8月6日(水)／北陸は激しい雷雨のおそれ　太平洋側は猛暑と急な雨〈ウェザーニュースLiVEイブニング・駒木 結衣／宇野沢 達也〉","date":"2025-08-06","sec":11484,"caster":"駒木 結衣","weather":"宇野沢達也"},{"id":"PsZt4WcBW1M","title":"【ライブ配信終了】最新天気ニュース・地震情報 2025年8月6日(水)北陸は激しい雷雨のおそれ　太平洋側は猛暑と急な雨〈ウェザーニュースLiVEアフタヌーン・魚住茉由／宇野沢達也〉","date":"2025-08-06","sec":12491,"caster":"魚住 茉由","weather":"宇野沢達也"},{"id":"CD9eKuE4qTs","title":"【ライブ配信終了】最新天気ニュース・地震情報 2025年8月6日(水)／北陸は激しい雨のおそれ 関東から九州は暑さが続く〈ウェザーニュースLiVEコーヒータイム・田辺真南葉／飯島栄一〉","date":"2025-08-06","sec":12775,"caster":"田辺 真南葉","weather":"飯島栄一"},{"id":"BBXTSkJX0EY","title":"【ライブカメラ】「白浜大浜ビーチ」静岡県 下田市/2025年8月6日(水)","date":"2025-08-05","sec":42899},{"id":"mGc-WPHbPHA","title":"【ライブ配信終了】最新天気ニュース・地震情報 2025年8月6日(水)／北陸は激しい雨のおそれ 関東から九州は暑さが続く〈ウェザーニュースLiVEサンシャイン・小川千奈／飯島栄一〉","date":"2025-08-05","sec":12463,"caster":"小川 千奈","weather":"飯島栄一"},{"id":"TMqvtzTuVwE","title":"【ライブ配信終了】最新天気ニュース・地震情報 2025年8月6日(水)／厳暑続く 北陸などは激しい雨も〈ウェザーニュースLiVEモーニング・小林李衣奈／飯島栄一〉","date":"2025-08-05","sec":12616,"caster":"小林 李衣奈","weather":"飯島栄一"},{"id":"TOo1FADOCCY","title":"【ライブ配信終了】最新天気ニュース・地震情報 2025年8月6日(水)1:00〜／〈ウェザーニュースLiVE〉","date":"2025-08-05","sec":14405},{"id":"-rz9_b-qfEI","title":"【ライブ配信終了】最新天気ニュース・地震情報 2025年8月5日(火)／北陸や東北は明日にかけて激しい雨のおそれ〈ウェザーニュースLiVEムーン・戸北 美月／山口 剛央〉","date":"2025-08-05","sec":19053,"caster":"戸北 美月","weather":"山口剛央"},{"id":"JHs_ovaoSFo","title":"【4画面ライブ】41.8℃を観測 国内最高気温更新／40℃以上地点数も過去最多 関東など危険な暑さ／各地の気温実況監視／最大限の熱中症予防を／2025年8月5日(火)","date":"2025-08-05","sec":42901},{"id":"yMc1hyBJ9g0","title":"【ライブ配信終了】最新天気ニュース・地震情報 2025年8月5日(火)／歴代最高気温の41.8℃を群馬県伊勢崎で観測　関東は酷暑警戒〈ウェザーニュースLiVEイブニング・岡本結子リサ／山口剛央〉","date":"2025-08-05","sec":11315,"caster":"岡本 結子 リサ","weather":"山口剛央"},{"id":"vQrSH11RbSQ","title":"【ライブ配信終了】歴代最高気温の41.8℃を群馬県伊勢崎で観測 関東は酷暑警戒／最新天気ニュース・地震情報 2025年8月5日(火)〈ウェザーニュースLiVEアフタヌーン・山岸愛梨／山口剛央〉","date":"2025-08-05","sec":12964,"caster":"山岸 愛梨","weather":"山口剛央"},{"id":"nX8ozTbY6qU","title":"【ライブ配信終了】最新天気ニュース・地震情報 2025年8月5日(火)／群馬県桐生で41.2℃観測 歴代最高気温に並ぶ 関東は酷暑警戒〈ウェザーニュースLiVEコーヒータイム・田辺真南葉／飯島栄一〉","date":"2025-08-05","sec":12254,"caster":"田辺 真南葉","weather":"飯島栄一"},{"id":"z-nKhvxZLrc","title":"【ライブ配信終了】最新天気ニュース・地震情報 2025年8月5日(火)／関東で40℃超えの可能性 北陸や北日本は強雨に注意〈ウェザーニュースLiVEサンシャイン・松本真央／飯島栄一〉","date":"2025-08-04","sec":11665,"caster":"松本 真央","weather":"飯島栄一"},{"id":"-OXpP7xNKtk","title":"【ライブ配信終了】最新天気ニュース・地震情報 2025年8月5日(火)／関東で40℃超えの可能性 北陸や北日本は強雨に注意〈ウェザーニュースLiVEモーニング・小林李衣奈／飯島栄一〉","date":"2025-08-04","sec":12425,"caster":"小林 李衣奈","weather":"飯島栄一"},{"id":"epW5xDoxr-A","title":"【ライブカメラ】幕張からの夜景 ／千葉県千葉市美浜区 ウェザーニュースお天気カメラ 2025年8月4日(月)","date":"2025-08-04","sec":24685},{"id":"q3uq16KLCdI","title":"【ライブ配信終了】最新天気ニュース・地震情報 2025年8月5日(火)1:00〜／北日本や北陸は傘の出番　関東は酷暑に警戒〈ウェザーニュースLiVE〉","date":"2025-08-04","sec":13461},{"id":"RGT89avvnUg","title":"【ライブ配信終了】最新天気ニュース・地震情報 2025年8月4日(月)20:00〜／北日本や九州は天気崩れる〈ウェザーニュースLiVEムーン・戸北 美月／芳野 達郎〉","date":"2025-08-04","sec":19219,"caster":"戸北 美月","weather":"芳野達郎"},{"id":"6XoYMXPj1Wc","title":"【ライブ配信終了】最新天気ニュース・地震情報 2025年8月4日(月)／近畿から関東で猛暑継続　北日本や九州は天気崩れる〈ウェザーニュースLiVEイブニング・山岸 愛梨／芳野 達郎〉","date":"2025-08-04","sec":13150,"caster":"山岸 愛梨","weather":"芳野達郎"},{"id":"w7gaSRAa9PI","title":"【ライブ配信終了】最新天気ニュース・地震情報 2025年8月4日(日)／近畿から関東で猛暑継続　北日本や九州は天気崩れる〈ウェザーニュースLiVEアフタヌーン・青原桃香／芳野達郎〉","date":"2025-08-04","sec":12399,"caster":"青原 桃香","weather":"芳野達郎"},{"id":"pLuEfLPPXwI","title":"【ライブ配信終了】最新天気ニュース・地震情報 2025年8月4日(月)／近畿から関東で猛暑継続　北日本や九州は天気崩れる〈ウェザーニュースLiVEコーヒータイム・川畑玲／山口剛央〉","date":"2025-08-04","sec":11893,"caster":"川畑 玲","weather":"山口剛央"},{"id":"7p3LupHcQIg","title":"【ライブカメラ】「白浜大浜ビーチ」静岡県 下田市/2025年8月4日(月)","date":"2025-08-03","sec":42899},{"id":"FFzDEzz8YzE","title":"【ライブ配信終了】最新天気ニュース・地震情報 2025年8月4日(月)／近畿から関東で猛暑継続　北日本や九州は天気崩れる〈ウェザーニュースLiVEサンシャイン・松本真央／山口剛央〉","date":"2025-08-03","sec":12111,"caster":"松本 真央","weather":"山口剛央"},{"id":"cgDOfaXWh_Q","title":"【ライブ配信終了】最新天気ニュース・地震情報 2025年8月4日(月)／近畿から関東で猛暑継続　北日本や九州は天気崩れる〈ウェザーニュースLiVEモーニング・福吉貴文／山口剛央〉","date":"2025-08-03","sec":12099,"caster":"福吉 貴文","weather":"山口剛央"},{"id":"U0sB_wCjQcM","title":"【ライブカメラ】幕張から東京・千葉の夜景／千葉県千葉市美浜区 ウェザーニュースお天気カメラ 2025年8月3日(日)","date":"2025-08-03","sec":38817},{"id":"QmlajI7_6fs","title":"【ライブ配信終了】最新天気ニュース・地震情報 2025年8月4日(月)1:00〜／近畿から関東で猛暑継続　北日本や九州は天気崩れる〈ウェザーニュースLiVE〉","date":"2025-08-03","sec":13539},{"id":"leJQNkaLALs","title":"【ライブ配信終了】最新天気ニュース・地震情報 2025年8月3日(日)／夜も危険な暑さ続く 万全な熱中症対策を〈ウェザーニュースLiVEムーン・岡本 結子リサ／森田 清輝〉","date":"2025-08-03","sec":18735,"caster":"岡本 結子 リサ","weather":"森田清輝"},{"id":"8MQerB70Fqo","title":"【4K＆高音質】長岡花火花火中継｜🤍🕊️✨🫶｜【8月3日(日)】＜メイン＞","date":"2025-08-03","sec":10140},{"id":"lxEjwxZBjAs","title":"【4K＆高音質】長岡花火花火中継｜🤍🕊️✨🫶｜【8月3日(日)】＜引き固定＞","date":"2025-08-03","sec":8620},{"id":"GLHVnPvDkjc","title":"【ライブ配信終了】最新天気ニュース・地震情報 2025年8月3日(日)／危険な暑さ続く 万全な熱中症対策を〈ウェザーニュースLiVEイブニング・山岸愛梨／森田清輝〉","date":"2025-08-03","sec":11372,"caster":"山岸 愛梨","weather":"森田清輝"},{"id":"QhwCB0uWD6M","title":"【ライブ配信終了】最新天気ニュース・地震情報 2025年8月3日(日)／危険な暑さ続く 万全な熱中症対策を〈ウェザーニュースLiVEアフタヌーン・小川千奈／森田清輝〉","date":"2025-08-03","sec":12092,"caster":"小川 千奈","weather":"森田清輝"},{"id":"BBb-Tc2aBv0","title":"【ライブ配信終了】最新天気ニュース・地震情報 2025年8月3日(日)／危険な暑さ続く 万全な熱中症対策を〈ウェザーニュースLiVEコーヒータイム・田辺真南葉／山口剛央〉","date":"2025-08-03","sec":11501,"caster":"田辺 真南葉","weather":"山口剛央"},{"id":"3091n8XMdiY","title":"【ライブカメラ】「白浜大浜ビーチ」静岡県 下田市/2025年8月3日(日)","date":"2025-08-02","sec":37563},{"id":"RV4qITVhmFw","title":"【ライブ配信終了】最新天気ニュース・地震情報 2025年8月3日(日)／危険な暑さ続く 万全な熱中症対策を〈ウェザーニュースLiVEサンシャイン・小林李衣奈／山口 剛央〉","date":"2025-08-02","sec":12641,"caster":"小林 李衣奈","weather":"山口剛央"},{"id":"qJVNvfB_eU0","title":"【ライブ配信】最新天気ニュース・地震情報 2025年8月3日(日)／危険な暑さ続く 万全な熱中症対策を〈ウェザーニュースLiVEモーニング・魚住 茉由／山口剛央〉","date":"2025-08-02","sec":12449,"caster":"魚住 茉由","weather":"山口剛央"},{"id":"zdRxHYImqB0","title":"【ライブ配信終了】最新天気ニュース・地震情報 2025年8月3日(金)1:00〜／〈ウェザーニュースLiVE〉","date":"2025-08-02","sec":14101},{"id":"LTZ1tS_68To","title":"【ライブカメラ】幕張からの夜景と...花火／千葉県千葉市美浜区 ウェザーニュースお天気カメラ 2025年8月2日(土)","date":"2025-08-02","sec":19685},{"id":"jZpzUMcgb60","title":"【ライブ配信終了】最新天気ニュース・地震情報 2025年8月2日(土)20:00〜／太平洋津波警報センターの話／台風9号は東海上へ〈ウェザーニュースLiVEムーン・駒木 結衣／森田 清輝〉","date":"2025-08-02","sec":17882,"caster":"駒木 結衣","weather":"森田清輝"},{"id":"HDhvV3ELfhw","title":"【4K高音質!花火中継!!】長岡花火2025 🎆 あなたの「感情の絵文字」で夜空（チャット欄）を彩ろう！🤍🕊️✨🫶｜【8月2日(土)】＜メイン＞","date":"2025-08-02","sec":10296},{"id":"Xte3NgSUBcY","title":"【4K高音質!花火中継!!】長岡花火2025 🎆 あなたの「感情の絵文字」で夜空（チャット欄）を彩ろう！🤍🕊️✨🫶｜【8月2日(土)】＜引き固定＞","date":"2025-08-02","sec":8535},{"id":"T_rEj_wcArc","title":"【ライブ配信終了】最新天気ニュース・地震情報 2025年8月2日(土)／台風9号は東海上へ 西日本や東海は猛暑〈ウェザーニュースLiVEイブニング・戸北美月／森田清輝〉","date":"2025-08-02","sec":11303,"caster":"戸北 美月","weather":"森田清輝"},{"id":"FAPM7qgHfoA","title":"【ライブ配信終了】最新天気ニュース・地震情報 2025年8月2日(土)／台風9号は東海上へ 西日本や東海は猛暑〈ウェザーニュースLiVEアフタヌーン・山岸愛梨／森田清輝〉","date":"2025-08-02","sec":12099,"caster":"山岸 愛梨","weather":"森田清輝"},{"id":"ioKUqS6AxsY","title":"【ライブ配信終了】最新天気ニュース・地震情報 2025年8月2日(土)／台風9号は東海上へ 西日本や東海は猛暑〈ウェザーニュースLiVEコーヒータイム・松本真央／山口剛央〉","date":"2025-08-02","sec":12583,"caster":"松本 真央","weather":"山口剛央"},{"id":"r-_zIPw-faQ","title":"【ライブ配信終了】最新天気ニュース・地震情報 2025年8月2日(土)／台風9号は東海上へ 西日本や東海は猛暑〈ウェザーニュースLiVEサンシャイン・田辺真南葉／山口 剛央〉","date":"2025-08-01","sec":12304,"caster":"田辺 真南葉","weather":"山口剛央"},{"id":"_ao86US0A3k","title":"【ライブ配信終了】最新天気ニュース・地震情報 2025年8月2日(土)／台風9号は東海上へ 西日本や東海は猛暑〈ウェザーニュースLiVEモーニング・小林 李衣奈／山口 剛央〉","date":"2025-08-01","sec":12120,"caster":"小林 李衣奈","weather":"山口剛央"},{"id":"ZX5GhuFA1gI","title":"【ライブ配信終了】最新天気ニュース・地震情報 2025年8月1日(金)23:00〜／台風9号が関東に最接近〈ウェザーニュースLiVE・小川千奈〉","date":"2025-08-01","sec":21671,"caster":"小川 千奈"},{"id":"90ZS_7ZUnzk","title":"【雨風ライブカメラ】関東 雨風の強まりに注意/ 千葉県 鴨川市 2025年8月1日(金)","date":"2025-08-01","sec":42900},{"id":"NZg_4KKL4Z4","title":"【ライブ配信終了】最新天気ニュース・地震情報 2025年8月1日(金)20:00〜／台風9号の影響に警戒〈ウェザーニュースLiVEムーン・駒木結衣／宇野沢達也〉","date":"2025-08-01","sec":11145,"caster":"駒木 結衣","weather":"宇野沢達也"},{"id":"VBgBvaky27Q","title":"【ライブ配信終了】最新天気ニュース・地震情報 2025年8月1日(金)／三重県桑名で40℃観測 関東など台風9号の影響注意〈ウェザーニュースLiVEイブニング・岡本結子リサ／宇野沢達也〉","date":"2025-08-01","sec":10998,"caster":"岡本 結子 リサ","weather":"宇野沢達也"},{"id":"FVYTMVlHI0E","title":"【ライブ配信終了】最新天気ニュース・地震情報 2025年8月1日(金)／危険な暑さ続く 関東など台風9号の影響注意〈ウェザーニュースLiVEアフタヌーン・白井ゆかり／宇野沢達也〉","date":"2025-08-01","sec":12699,"caster":"白井 ゆかり","weather":"宇野沢達也"},{"id":"3cJC0A6hvVw","title":"【ライブ配信終了】最新天気ニュース・地震情報 2025年8月1日(金)／8月スタートも酷暑 関東や東北太平洋側は台風9号の接近に注意〈ウェザーニュースLiVEコーヒータイム・松本真央／山口剛央〉","date":"2025-08-01","sec":12264,"caster":"松本 真央","weather":"山口剛央"},{"id":"eJYsVngUnAk","title":"【気候変動番組】100年天気予報・夏休み企画~CO₂ってホントに減るの？植物のチカラ、自由研究で見てみた！〜/2025年8月1日(金)12:00~/魚住茉由・吉良真由子","date":"2025-08-01","sec":2552,"caster":"魚住 茉由"},{"id":"rpIDBn2s__M","title":"【ライブ配信終了】最新天気ニュース・地震情報 2025年8月1日(金)／関東や東北太平洋側は台風9号の接近に注意〈ウェザーニュースLiVEサンシャイン・小林李衣奈／山口 剛央〉","date":"2025-07-31","sec":12638,"caster":"小林 李衣奈","weather":"山口剛央"},{"id":"LOHBTaShxk0","title":"【ライブ配信終了】最新天気ニュース・地震情報 2025年8月1日(金)／台風が関東に今夜最接近し雨風強まるおそれ〈ウェザーニュースLiVEモーニング・福吉貴文／山口剛央〉","date":"2025-07-31","sec":13321,"caster":"福吉 貴文","weather":"山口剛央"},{"id":"f9t3iEOVr0c","title":"【ライブ配信終了】最新天気ニュース・地震情報 2025年8月1日(金)1:00〜／8月は猛暑でスタート 関東は台風9号の影響注意〈ウェザーニュースLiVE〉","date":"2025-07-31","sec":13645},{"id":"TEbBKoPNDmI","title":"【天体ライブ】みずがめ座δ(デルタ)南流星群2025  ライブカメラ 福島県・星の村天文台／2025年7月31日(木)〈ウェザーニュースLiVE〉","date":"2025-07-31","sec":22509},{"id":"-k-0440PzyY","title":"【天体ライブ】みずがめ座δ(デルタ)南流星群2025  4K高画質ライブカメラ 静岡県富士宮市・富士山／2025年7月31日(木)〈ウェザーニュースLiVE〉","date":"2025-07-31","sec":19969},{"id":"mthHar1Vbj4","title":"【天体ライブ】みずがめ座δ(デルタ)南流星群2025  ライブカメラ 徳島県・阿南市科学センター／2025年7月31日(木)〈ウェザーニュースLiVE〉","date":"2025-07-31","sec":21945},{"id":"XCUxajjNGf4","title":"【ライブ配信終了】最新天気ニュース・地震情報 2025年7月31日(木)／台風9号は週末に関東接近のおそれ〈ウェザーニュースLiVEムーン・岡本 結子リサ／本田 竜也〉","date":"2025-07-31","sec":19508,"caster":"岡本 結子 リサ","weather":"本田竜也"},{"id":"d-oEO7uix6w","title":"【ライブカメラ】灯ろう流し-皇居・千鳥ヶ淵-／2025年7月31日(木) 18:00~","date":"2025-07-31","sec":9921},{"id":"mLBoacFAZYg","title":"【ライブ配信終了】最新天気ニュース・地震情報 2025年7月31日(木)／台風9号は週末に関東接近のおそれ〈ウェザーニュースLiVEイブニング・戸北美月／本田竜也〉","date":"2025-07-31","sec":11329,"caster":"戸北 美月","weather":"本田竜也"},{"id":"IAFWJRmtPLU","title":"【ライブ配信終了】津波注意報はすべて解除／最新天気ニュース・地震情報 2025年7月31日(木)／台風9号は週末に関東接近のおそれ〈ウェザーニュースLiVEアフタヌーン・小川千奈／本田竜也〉","date":"2025-07-31","sec":12386,"caster":"小川 千奈","weather":"本田竜也"},{"id":"2LaV7hsBghk","title":"【ライブ配信終了】最新天気ニュース・地震情報 2025年7月31日(木)／台風9号は週末に関東接近のおそれ 日本の沿岸に津波注意報発表中〈ウェザーニュースLiVEコーヒータイム・田辺真南葉／飯島栄一〉","date":"2025-07-31","sec":11699,"caster":"田辺 真南葉","weather":"飯島栄一"},{"id":"hN13qNZ1iNU","title":"【ライブ配信】すべての津波注意報が解除　カムチャツカ半島付近M8.7の地震 　4画面配信","date":"2025-07-30","sec":33948},{"id":"2C6VJlZ5res","title":"【ライブ配信終了】最新天気ニュース・地震情報 2025年7月31日(木)／台風9号は週末関東に接近のおそれ 日本の沿岸に津波注意報発表中〈ウェザーニュースLiVEサンシャイン・魚住茉由／飯島栄一〉","date":"2025-07-30","sec":12416,"caster":"魚住 茉由","weather":"飯島栄一"},{"id":"xHhOlKAHuKs","title":"【ライブ配信終了】最新天気ニュース・地震情報 2025年7月31日(木)／台風9号は週末関東に接近のおそれ 日本の沿岸に津波注意報発表中〈ウェザーニュースLiVEモーニング・福吉貴文／飯島栄一〉","date":"2025-07-30","sec":13162,"caster":"福吉 貴文","weather":"飯島栄一"},{"id":"9RqpkcjCwYY","title":"【ライブ配信終了】津波警報は津波注意報に・カムチャツカ半島付近でM8.7の地震／最新天気ニュース・地震情報 2025年7月30日(水)〈ウェザーニュースLiVEムーン・岡本 結子リサ／内藤 邦裕〉","date":"2025-07-30","sec":32579,"caster":"岡本 結子 リサ","weather":"内藤邦裕"},{"id":"DLubn9CdQ2w","title":"【ライブ配信終了】津波警報発表・カムチャツカ半島付近でM8.7の地震／最新天気ニュース・地震情報 2025年7月30日(水)〈ウェザーニュースLiVEアフタヌーン・小川千奈／内藤邦裕〉","date":"2025-07-30","sec":21414,"caster":"小川 千奈","weather":"内藤邦裕"},{"id":"pRr7f0zGRnU","title":"【ライブ配信終了】太平洋側各地に津波警報 発表　ロシア・カムチャッカ付近でM8.7の地震　4画面配信","date":"2025-07-30","sec":4160},{"id":"mzy8ls17KK8","title":"【ライブカメラ】津波警報発表中「白浜大浜ビーチ」静岡県 下田市/2025年7月30日(水)","date":"2025-07-29","sec":42899},{"id":"Hf3oQ0kPlho","title":"【ライブ配信終了】津波警報発表・カムチャツカ半島付近でM8.7の地震 〈ウェザーニュースLiVEコーヒータイム・白井ゆかり／山口剛央〉最新天気ニュース・地震情報 2025年7月30日(水)","date":"2025-07-29","sec":25291,"caster":"白井 ゆかり","weather":"山口剛央"},{"id":"8gQYvpxaz70","title":"【4画面ライブ】津波警報　カムチャツカ半島付近でM8.7の地震","date":"2025-07-29","sec":4341},{"id":"MLjD1nezpuI","title":"【ライブ配信終了】最新天気ニュース・地震情報 2025年7月30日(水)／40℃前後の危険な暑さに警戒〈ウェザーニュースLiVEモーニング・青原桃香／飯島栄一〉","date":"2025-07-29","sec":12219,"caster":"青原 桃香","weather":"飯島栄一"},{"id":"bC6NXgcj5yw","title":"【ライブ配信終了】最新天気ニュース・地震情報 2025年7月30日(水)1:00〜／〈ウェザーニュースLiVE〉","date":"2025-07-29","sec":14167},{"id":"xheKUygflfE","title":"【ライブ配信終了】最新天気ニュース・地震情報 2025年7月29日(火)／台風8号・9号の影響に注意 熱中症予防DAY〈ウェザーニュースLiVEムーン・戸北 美月／山口 剛央〉","date":"2025-07-29","sec":20279,"caster":"戸北 美月","weather":"山口剛央"},{"id":"WL_nMZ12ghM","title":"【ライブカメラ】幕張から東京・千葉の夜景 細い月の様子も／千葉県千葉市美浜区 ウェザーニュースお天気カメラ 2025年7月29日(火)","date":"2025-07-29","sec":20462},{"id":"ph7pdxALrIM","title":"【ライブ配信終了】2025最新熱中症予防グッズ紹介  2025年7月29日(火)21:00〜／サンコー株式会社 ekky・戸北美月〈ウェザーニュースLiVE・熱中症予防DAY〉","date":"2025-07-29","sec":2967,"caster":"戸北 美月"},{"id":"Z_7vkRQ0_1Y","title":"【ライブ配信終了】最新天気ニュース・地震情報 2025年7月29日(火)／熱中症予防DAY　群馬県で39.9℃　猛暑日地点は過去最多に〈ウェザーニュースLiVEイブニング・駒木結衣／山口剛央〉","date":"2025-07-29","sec":11384,"caster":"駒木 結衣","weather":"山口剛央"},{"id":"e2DypSFLuj0","title":"【ライブ配信終了】最新天気ニュース・地震情報 2025年7月29日(火)／熱中症予防DAY 気温上昇で危険な暑さ 40℃に迫るところも〈ウェザーニュースLiVEアフタヌーン・小川千奈／山口剛央〉","date":"2025-07-29","sec":12523,"caster":"小川 千奈","weather":"山口剛央"},{"id":"us5taJhXTi4","title":"【ライブ配信終了】最新天気ニュース・地震情報 2025年7月29日(火)／熱中症予防DAY・40℃に迫る危険な暑さに警戒〈ウェザーニュースLiVEコーヒータイム・田辺真南葉／本田竜也〉","date":"2025-07-29","sec":10945,"caster":"田辺 真南葉","weather":"本田竜也"},{"id":"EaOC5lmIhaY","title":"【ライブカメラ】「白浜大浜ビーチ」@静岡県 下田市/2025年7月29日(火)","date":"2025-07-28","sec":42900},{"id":"jhqIrFIQqiI","title":"【ライブ配信終了】最新天気ニュース・地震情報 2025年7月29日(火)／熱中症予防DAY／広範囲で危険な暑さが続く〈ウェザーニュースLiVEサンシャイン・松本真央／本田竜也〉","date":"2025-07-28","sec":12153,"caster":"松本 真央","weather":"本田竜也"},{"id":"01b2IXi7N1U","title":"【ライブ配信終了】最新天気ニュース・地震情報 2025年7月29日(火)／熱中症予防DAY〈ウェザーニュースLiVEモーニング・青原桃香／本田竜也〉","date":"2025-07-28","sec":12589,"caster":"青原 桃香","weather":"本田竜也"},{"id":"MzvUACSPJE4","title":"【ライブ配信終了】最新天気ニュース・地震情報 2025年7月29日(火)1:00〜／広範囲で危険な暑さが続く〈ウェザーニュースLiVE〉","date":"2025-07-28","sec":12471},{"id":"LD14EsS9VU0","title":"【ライブカメラ】幕張から東京・千葉の夜景 細い月の様子も／千葉県千葉市美浜区 ウェザーニュースお天気カメラ 2025年7月28日","date":"2025-07-28","sec":30799},{"id":"SdtMjOzIvYs","title":"【ライブ配信終了】最新天気ニュース・地震情報 2025年7月28日(月)／広範囲で猛暑が続く・台風8号9号警戒〈ウェザーニュースLiVEムーン・戸北 美月／山口 剛央〉","date":"2025-07-28","sec":20315,"caster":"戸北 美月","weather":"山口剛央"},{"id":"yMgejxh0l54","title":"【ライブ配信終了】最新天気ニュース・地震情報 2025年7月28日(月)／広範囲で猛暑が続く・台風8号9号警戒〈ウェザーニュースLiVEイブニング・岡本 結子リサ／山口 剛央〉","date":"2025-07-28","sec":11561,"caster":"岡本 結子 リサ","weather":"山口剛央"},{"id":"DasF4pnOOX0","title":"【ライブ配信終了】最新天気ニュース・地震情報 2025年7月28日(月)／広範囲で猛暑が続く・台風8号9号警戒〈ウェザーニュースLiVEアフタヌーン・江川清音／山口剛央〉","date":"2025-07-28","sec":12171,"caster":"江川 清音","weather":"山口剛央"},{"id":"oPOcCG4B0Kg","title":"【ライブ配信終了】最新天気ニュース・地震情報 2025年7月28日(月)／広範囲で猛暑が続く・台風8号9号警戒〈ウェザーニュースLiVEコーヒータイム・田辺真南葉／芳野達郎〉","date":"2025-07-28","sec":11602,"caster":"田辺 真南葉","weather":"芳野達郎"},{"id":"t6dlUBv-NNk","title":"【ライブカメラ】「白浜大浜ビーチ」@静岡県 下田市/2025年7月28日(月)","date":"2025-07-27","sec":42899},{"id":"HJC3txbwniA","title":"【ライブ配信終了】最新天気ニュース・地震情報 2025年7月28日(月)／今日も危険な暑さ 熱中症に警戒を〈ウェザーニュースLiVEサンシャイン・青原桃香／芳野達郎〉","date":"2025-07-27","sec":12042,"caster":"青原 桃香","weather":"芳野達郎"},{"id":"L5gZCSLnKTM","title":"【ライブ配信終了】最新天気ニュース・地震情報 2025年7月28日(月)／広範囲で猛暑が続く・台風8号9号警戒〈ウェザーニュースLiVEモーニング・福吉貴文／芳野達郎〉","date":"2025-07-27","sec":12452,"caster":"福吉 貴文","weather":"芳野達郎"},{"id":"87HWXr8xtCI","title":"【ライブカメラ】幕張から東京・千葉の夜景／千葉県千葉市美浜区 ウェザーニュースお天気カメラ 2025年7月27日","date":"2025-07-27","sec":32338},{"id":"0abE7jQPA4k","title":"【ライブ配信終了】最新天気ニュース・地震情報 2025年7月28日(月)1:00〜／真夏の強い日差し 広範囲で猛暑が続く〈ウェザーニュースLiVE〉","date":"2025-07-27","sec":12655},{"id":"RyzGGAL1X34","title":"【ライブ配信終了】最新天気ニュース・地震情報 2025年7月27日(日)／今年は日本近海の海水温が低い！？〈ウェザーニュースLiVEムーン・山岸 愛梨／森田 清輝〉","date":"2025-07-27","sec":19019,"caster":"山岸 愛梨","weather":"森田清輝"},{"id":"kG3pFSWiZos","title":"【厳選BEST版】4K HDRの尺玉300連発の迫力が…｜ぎおん柏崎まつり・海の大花火大会2025 (3D立体音響)","date":"2025-07-27","sec":2638},{"id":"4OybwwYuTlA","title":"【ライブ配信終了】最新天気ニュース・地震情報 2025年7月27日(日)／九州から関東は危険な暑さ　沖縄は激しい雨のおそれ〈ウェザーニュースLiVEイブニング・岡本 結子リサ／森田 清輝〉","date":"2025-07-27","sec":11335,"caster":"岡本 結子 リサ","weather":"森田清輝"},{"id":"XfXSueWOvls","title":"【ライブ配信終了】最新天気ニュース・地震情報 2025年7月27日(日)／九州から関東は危険な暑さ　沖縄は激しい雨のおそれ〈ウェザーニュースLiVEアフタヌーン・小川千奈／森田清輝〉","date":"2025-07-27","sec":12121,"caster":"小川 千奈","weather":"森田清輝"},{"id":"H09eXDjXUxk","title":"【ライブ配信終了】最新天気ニュース・地震情報 2025年7月27日(日)／九州から関東は危険な暑さ　沖縄は激しい雨のおそれ〈ウェザーニュースLiVEコーヒータイム・松本真央／山口 剛央〉","date":"2025-07-27","sec":12559,"caster":"松本 真央","weather":"山口剛央"},{"id":"T5GBVJCcbnc","title":"【ライブカメラ】「白浜大浜ビーチ」@静岡県 下田市/2025年7月27日(日)","date":"2025-07-26","sec":42900},{"id":"vOzOiz_1xz4","title":"【ライブ配信終了】最新天気ニュース・地震情報 2025年7月27日(日)／九州から関東は危険な暑さ　沖縄は激しい雨のおそれ〈ウェザーニュースLiVEサンシャイン・魚住茉由／山口 剛央〉","date":"2025-07-26","sec":12525,"caster":"魚住 茉由","weather":"山口剛央"},{"id":"iZ6N00eQLoU","title":"【ライブ配信終了】最新天気ニュース・地震情報 2025年7月27日(日)／九州から関東は危険な暑さ　沖縄は激しい雨のおそれ〈ウェザーニュースLiVEモーニング・小林 李衣奈／山口剛央〉","date":"2025-07-26","sec":12488,"caster":"小林 李衣奈","weather":"山口剛央"},{"id":"s95tNYd5NAU","title":"【ライブ配信終了】最新天気ニュース・地震情報 2025年7月27日(日)1:00〜／九州から関東は危険な暑さ　沖縄は激しい雨のおそれ〈ウェザーニュースLiVE〉","date":"2025-07-26","sec":14145},{"id":"uHKxnE66YBs","title":"【ライブ配信終了】最新天気ニュース・地震情報 2025年7月26日(土)／台風8号接近　沖縄や西日本太平洋側は強雨に注意〈ウェザーニュースLiVEムーン・山岸 愛梨／森田 清輝〉","date":"2025-07-26","sec":18701,"caster":"山岸 愛梨","weather":"森田清輝"},{"id":"kngJXd7OUjs","title":"【ライブ配信終了】最新天気ニュース・地震情報 2025年7月26日(土)／酷暑の週末　九州や沖縄は激しい雨のおそれ〈ウェザーニュースLiVEイブニング・戸北 美月／森田 清輝〉","date":"2025-07-26","sec":11540,"caster":"戸北 美月","weather":"森田清輝"},{"id":"tIfvnA-LdjM","title":"【ライブ配信終了】最新天気ニュース・地震情報 2025年7月26日(土)／広範囲で厳しい暑さが続く　沖縄は台風の影響に注意〈ウェザーニュースLiVEアフタヌーン・松本真央／森田清輝〉","date":"2025-07-26","sec":11219,"caster":"松本 真央","weather":"森田清輝"},{"id":"8fWhEIAltbQ","title":"【ライブ配信終了】最新天気ニュース・地震情報 2025年7月26日(土)／酷暑の週末　台風8号が沖縄に接近〈ウェザーニュースLiVEコーヒータイム・田辺真南葉／山口剛央〉","date":"2025-07-26","sec":12797,"caster":"田辺 真南葉","weather":"山口剛央"},{"id":"B2-_uG-25hs","title":"【ライブカメラ】「白浜大浜ビーチ」@静岡県 下田市/2025年7月26日(土)","date":"2025-07-25","sec":42899},{"id":"jQouXuqMjls","title":"【ライブ配信終了】最新天気ニュース・地震情報 2025年7月26日(土)／酷暑の週末　台風8号が沖縄に接近〈ウェザーニュースLiVEサンシャイン・魚住茉由／山口 剛央〉","date":"2025-07-25","sec":12532,"caster":"魚住 茉由","weather":"山口剛央"},{"id":"spDe6bdaB3k","title":"【ライブ配信終了】最新天気ニュース・地震情報 2025年7月26日(土)／酷暑の週末　台風8号が沖縄に接近〈ウェザーニュースLiVEモーニング・小林 李衣奈／山口 剛央〉","date":"2025-07-25","sec":13399,"caster":"小林 李衣奈","weather":"山口剛央"},{"id":"G4_0i9AH2nE","title":"【ライブ配信終了】最新天気ニュース・地震情報 2025年7月26日(土)1:00〜／酷暑の週末　台風8号が沖縄に接近〈ウェザーニュースLiVE〉","date":"2025-07-25","sec":13883},{"id":"uK7ukuGWk3U","title":"【ライブカメラ終了】幕張から東京・千葉の夜景／千葉県千葉市美浜区 ウェザーニュースお天気カメラ 2025年7月25日","date":"2025-07-25","sec":28813},{"id":"HaK_-S5oTDg","title":"【ライブ配信終了】最新天気ニュース・地震情報 2025年7月25日(金)／酷暑の週末　台風8号が沖縄に接近〈ウェザーニュースLiVEムーン・駒木 結衣／宇野沢 達也〉","date":"2025-07-25","sec":12611,"caster":"駒木 結衣","weather":"宇野沢達也"},{"id":"D3v73TahFNw","title":"【JR東日本×ウェザーニュース】避暑旅タイアップ特別企画　第8回出演：駒木結衣 小川千奈","date":"2025-07-25","sec":2321,"caster":"小川 千奈"},{"id":"10I3pKMTG58","title":"【ライブ配信終了】最新天気ニュース・地震情報 2025年7月25日(金)／広範囲で厳しい暑さが続く　沖縄は台風の影響に注意〈ウェザーニュースLiVEムーン・駒木 結衣／宇野沢 達也〉","date":"2025-07-25","sec":3959,"caster":"駒木 結衣","weather":"宇野沢達也"},{"id":"9KGgKkUyQl8","title":"【ライブ配信終了】最新天気ニュース・地震情報 2025年7月25日(金)／広範囲で厳しい暑さが続く　沖縄は台風の影響に注意〈ウェザーニュースLiVEイブニング・岡本結子リサ／宇野沢達也〉","date":"2025-07-25","sec":11422,"caster":"岡本 結子 リサ","weather":"宇野沢達也"},{"id":"tDjUaHCq-TI","title":"【ライブ配信終了】最新天気ニュース・地震情報 2025年7月25日(金)／広範囲で厳しい暑さが続く　沖縄は台風の影響に注意〈ウェザーニュースLiVEアフタヌーン・戸北 美月／宇野沢 達也〉","date":"2025-07-25","sec":12551,"caster":"戸北 美月","weather":"宇野沢達也"},{"id":"zyGlSCcJtH4","title":"【ライブ配信終了】最新天気ニュース・地震情報 2025年7月25日(金)／広範囲で厳しい暑さが続く　沖縄は台風の影響に注意〈ウェザーニュースLiVEコーヒータイム・田辺 真南葉／山口 剛央〉","date":"2025-07-25","sec":12774,"caster":"田辺 真南葉","weather":"山口剛央"},{"id":"i6tbryAAVjk","title":"【気候変動番組】100年天気予報〜熱帯夜100日時代が来る！？今夜からできる熱中症対策〜/2025年7月25日(金)12:00~/魚住茉由・吉良真由子","date":"2025-07-25","sec":2139,"caster":"魚住 茉由"},{"id":"Y_FhN3luES4","title":"【ライブカメラ】「白浜大浜ビーチ」@静岡県 下田市/2025年7月25日(金)","date":"2025-07-24","sec":42899},{"id":"Rp4n8plnIiI","title":"【ライブ配信終了】最新天気ニュース・地震情報 2025年7月25日(金)／広範囲で厳しい暑さが続く　沖縄は台風の影響に注意〈ウェザーニュースLiVEサンシャイン・小林李衣奈／山口 剛央〉","date":"2025-07-24","sec":12421,"caster":"小林 李衣奈","weather":"山口剛央"},{"id":"fAWrEQRO5Do","title":"【ライブ配信終了】最新天気ニュース・地震情報 2025年7月25日(金)／広範囲で厳しい暑さが続く　沖縄は台風の影響に注意〈ウェザーニュースLiVEモーニング・福吉貴文／山口剛央〉","date":"2025-07-24","sec":13182,"caster":"福吉 貴文","weather":"山口剛央"},{"id":"u72z064JKdY","title":"【ライブ配信終了】最新天気ニュース・地震情報 2025年7月25日(金)1:00〜／広範囲で厳しい暑さが続く　沖縄は台風の影響に注意〈ウェザーニュースLiVE〉","date":"2025-07-24","sec":14607},{"id":"7RhrR6R721I","title":"【ライブ配信終了】最新天気ニュース・地震情報 2025年7月24日(木)／沖縄に台風7号接近〈ウェザーニュースLiVEムーン・駒木 結衣／芳野 達郎〉","date":"2025-07-24","sec":19195,"caster":"駒木 結衣","weather":"芳野達郎"},{"id":"ihNCkt19C8s","title":"【ライブ配信終了】最新天気ニュース・地震情報 2025年7月24日(木)／九州から北海道で危険な暑さ 沖縄は台風の影響で荒天注意〈ウェザーニュースLiVEイブニング・岡本結子リサ／芳野達郎〉","date":"2025-07-24","sec":11397,"caster":"岡本 結子 リサ","weather":"芳野達郎"},{"id":"plZVM__K1DA","title":"【ライブ配信終了】最新天気ニュース・地震情報 2025年7月24日(木)／九州から北海道で危険な暑さ 沖縄は台風の影響で荒天注意〈ウェザーニュースLiVEアフタヌーン・松本真央／芳野達郎〉","date":"2025-07-24","sec":12742,"caster":"松本 真央","weather":"芳野達郎"},{"id":"KOJAJVUNyhY","title":"【ライブ配信終了】最新天気ニュース・地震情報 2025年7月24日(木)／九州から北海道で危険な暑さ 沖縄は台風の影響で荒天注意〈ウェザーニュースLiVEコーヒータイム・田辺真南葉／飯島栄一〉","date":"2025-07-24","sec":11816,"caster":"田辺 真南葉","weather":"飯島栄一"},{"id":"op9Tt4fXAjs","title":"【ライブカメラ】「白浜大浜ビーチ」@静岡県 下田市/2025年7月24日(木)","date":"2025-07-23","sec":42899},{"id":"Gn_SzWefaHw","title":"【ライブ配信終了】最新天気ニュース・地震情報 2025年7月24日(木)／九州から北海道で危険な暑さ 沖縄は台風の影響で荒天注意〈ウェザーニュースLiVEサンシャイン・魚住茉由／本田竜也〉","date":"2025-07-23","sec":12744,"caster":"魚住 茉由","weather":"本田竜也"},{"id":"5wggM9oGODQ","title":"【ライブ配信終了】最新天気ニュース・地震情報 2025年7月24日(木)／危険な暑さと台風の影響に注意〈ウェザーニュースLiVEモーニング・福吉貴文／本田竜也〉","date":"2025-07-23","sec":12795,"caster":"福吉 貴文","weather":"本田竜也"},{"id":"jv9PA7TOt2M","title":"【ライブカメラ】幕張から東京・千葉の夜景／千葉県千葉市美浜区 ウェザーニュースお天気カメラ 2025年7月23日","date":"2025-07-23","sec":25291},{"id":"Lsxbw-KOn2w","title":"【ライブ配信終了】最新天気ニュース・地震情報 2025年7月24日(木)1:00〜／九州から北海道で危険な暑さ　沖縄は台風の影響で荒天〈ウェザーニュースLiVE〉","date":"2025-07-23","sec":12503},{"id":"o_jAoQ_Gly0","title":"【ライブ配信終了】最新天気ニュース・地震情報 2025年7月23日(水)／明日は九州から北海道で危険な暑さ〈ウェザーニュースLiVEムーン・駒木 結衣／宇野沢 達也〉","date":"2025-07-23","sec":20301,"caster":"駒木 結衣","weather":"宇野沢達也"},{"id":"V49srzAu5Nw","title":"【参加者求む！】あなたのコメントで花火を描きます！青原桃香と一緒に日本平まつりを楽しもう！","date":"2025-07-23","sec":6376,"caster":"青原 桃香"},{"id":"lT_DoiBzDAw","title":"【ライブ】第40回日本平まつり大花火ショー / 12,000発の絶景花火 / 日本夜景遺産","date":"2025-07-23","sec":4580},{"id":"BCfaatvOSCQ","title":"【ライブ配信終了】最新天気ニュース・地震情報 2025年7月23日(水)／南シナ海で新たな台風発生予想〈ウェザーニュースLiVEイブニング・戸北美月／宇野沢達也〉","date":"2025-07-23","sec":11330,"caster":"戸北 美月","weather":"宇野沢達也"},{"id":"7gMKU5XU2Jo","title":"【ライブ配信終了】最新天気ニュース・地震情報 2025年7月23日(水)／全国的な暑さ続く 広範囲で猛暑日に〈ウェザーニュースLiVEアフタヌーン・江川 清音／宇野沢 達也〉","date":"2025-07-23","sec":12306,"caster":"江川 清音","weather":"宇野沢達也"},{"id":"yaNU2nPmyf0","title":"【ライブ配信終了】最新天気ニュース・地震情報 2025年7月23日(水)／全国的な暑さ続く 広範囲で猛暑日に〈ウェザーニュースLiVEコーヒータイム・松本真央／飯島栄一〉","date":"2025-07-23","sec":12940,"caster":"松本 真央","weather":"飯島栄一"},{"id":"htjJBNxrhqA","title":"【ライブカメラ】「白浜大浜ビーチ」@静岡県 下田市/2025年7月23日(水)","date":"2025-07-22","sec":42900},{"id":"mtcnP2wlqZY","title":"【ライブ配信終了】最新天気ニュース・地震情報 2025年7月23日(水)／全国的な暑さ続く 北海道は広範囲で猛暑日に〈ウェザーニュースLiVEサンシャイン・小川千奈／飯島栄一〉","date":"2025-07-22","sec":12534,"caster":"小川 千奈","weather":"飯島栄一"},{"id":"es2SAZsFXsg","title":"【ライブ配信終了】最新天気ニュース・地震情報 2025年7月23日(水)／全国的な暑さ続く　ゲリラ雷雨に注意〈ウェザーニュースLiVEモーニング・小林李衣奈／飯島栄一〉","date":"2025-07-22","sec":12713,"caster":"小林 李衣奈","weather":"飯島栄一"},{"id":"k3CaTQMSVMQ","title":"【ライブ配信終了】最新天気ニュース・地震情報 2025年7月23日(水)1:00〜／全国的な暑さ続く　北海道は広範囲で猛暑日に〈ウェザーニュースLiVE〉","date":"2025-07-22","sec":13253},{"id":"5371_2_XeBY","title":"【ライブカメラ】幕張から東京・千葉の夜景／千葉県千葉市美浜区 ウェザーニュースお天気カメラ 2025年7月22日","date":"2025-07-22","sec":25376},{"id":"-AIv-Mh3maI","title":"【ライブ配信終了】最新天気ニュース・地震情報 2025年7月22日(火)／夜間も熱中症に警戒〈ウェザーニュースLiVEムーン・山岸 愛梨／山口 剛央〉","date":"2025-07-22","sec":19491,"caster":"山岸 愛梨","weather":"山口剛央"},{"id":"eu2fMGBHlPE","title":"【ライブ】第59回 葛飾納涼花火大会 2025｜1万5000発のフィナーレまで完全生中継＜メイン＞","date":"2025-07-22","sec":4760},{"id":"wElu5ycUBjw","title":"【ライブ】第59回 葛飾納涼花火大会 2025｜1万5000発のフィナーレまで完全生中継＜引き＞","date":"2025-07-22","sec":3526},{"id":"HerNcd-VXH0","title":"【ライブ配信終了】最新天気ニュース・地震情報 2025年7月22日(火)／関東甲信の山沿いで雷雨に注意〈ウェザーニュースLiVEイブニング・駒木 結衣／山口 剛央〉","date":"2025-07-22","sec":12682,"caster":"駒木 結衣","weather":"山口剛央"},{"id":"_-XkDMiLc-0","title":"【ライブ配信終了】最新天気ニュース・地震情報 2025年7月22日(火)／「大暑」らしく全国的に暑い　関東甲信の山沿いで雷雨に注意〈ウェザーニュースLiVEアフタヌーン・青原 桃香／山口 剛央〉","date":"2025-07-22","sec":11651,"caster":"青原 桃香","weather":"山口剛央"},{"id":"y5-uN3QVEoc","title":"【ライブ配信終了】最新天気ニュース・地震情報 2025年7月22日(火)／厳しい暑さと夏空続く　沖縄は熱帯低気圧の動向注意〈ウェザーニュースLiVEコーヒータイム・松本真央／飯島栄一〉","date":"2025-07-22","sec":11970,"caster":"松本 真央","weather":"飯島栄一"},{"id":"RQ8PI1HDFp4","title":"【ライブカメラ】「白浜大浜ビーチ」@静岡県 下田市/2025年7月22日(火)","date":"2025-07-21","sec":42899},{"id":"ICT4i72jsM0","title":"【ライブ配信終了】最新天気ニュース・地震情報 2025年7月22日(火)／三連休明けも真夏の日差し　万全な暑さ対策を〈ウェザーニュースLiVEサンシャイン・小林李衣奈／飯島栄一〉","date":"2025-07-21","sec":12408,"caster":"小林 李衣奈","weather":"飯島栄一"},{"id":"w044ZuqF6oM","title":"【ライブ配信終了】最新天気ニュース・地震情報 2025年7月22日(火)／三連休明けも真夏の日差し　万全な暑さ対策を〈ウェザーニュースLiVEモーニング・福吉貴文／飯島栄一〉","date":"2025-07-21","sec":12579,"caster":"福吉 貴文","weather":"飯島栄一"},{"id":"_CUWue7JpWc","title":"【ライブカメラ】幕張から東京・千葉の夜景／千葉県千葉市美浜区 ウェザーニュースお天気カメラ 2025年7月21日","date":"2025-07-21","sec":25635},{"id":"NWqyMQZJY3A","title":"【ライブ配信終了】最新天気ニュース・地震情報 2025年7月22日(火)1:00〜／三連休明けも万全な熱中症対策を〈ウェザーニュースLiVE〉","date":"2025-07-21","sec":13435},{"id":"HMRlRI3HYhU","title":"【ライブ配信終了】最新天気ニュース・地震情報 2025年7月21日(月)／三連休明けも真夏の日差し　万全な暑さ対策を〈ウェザーニュースLiVEムーン・岡本 結子リサ／山口 剛央〉","date":"2025-07-21","sec":18651,"caster":"岡本 結子 リサ","weather":"山口剛央"},{"id":"zKzZP-83k2c","title":"【ライブ配信終了】最新天気ニュース・地震情報 2025年7月21日(月)／長野県で記録的短時間大雨情報　関東甲信の山間部は要注意〈ウェザーニュースLiVEイブニング・山岸 愛梨／山口 剛央〉","date":"2025-07-21","sec":11658,"caster":"山岸 愛梨","weather":"山口剛央"},{"id":"SOFIWdJhTms","title":"【ライブ配信終了】最新天気ニュース・地震情報 2025年7月21日(月)／今日は海の日、連休最終日も厳しい暑さ〈ウェザーニュースLiVEアフタヌーン・戸北美月／山口剛央〉","date":"2025-07-21","sec":11795,"caster":"戸北 美月","weather":"山口剛央"},{"id":"8NQ_wd9PWR4","title":"【ライブ配信終了】最新天気ニュース・地震情報 2025年7月21日(月)／今日は海の日、連休最終日も厳しい暑さ〈ウェザーニュースLiVEコーヒータイム・青原桃香／芳野達郎〉","date":"2025-07-21","sec":12371,"caster":"青原 桃香","weather":"芳野達郎"},{"id":"kSYcvLTb7DI","title":"【海の日ライブカメラ】「白浜大浜ビーチ」@静岡県 下田市/2025年7月21日(月)　三連休最終日「海の日」","date":"2025-07-20","sec":42899},{"id":"tMAwImSVKBU","title":"【ライブ配信終了】最新天気ニュース・地震情報 2025年7月21日(月)／今日は海の日、連休最終日も厳しい暑さ〈ウェザーニュースLiVEサンシャイン・田辺真南葉／芳野達郎〉","date":"2025-07-20","sec":11680,"caster":"田辺 真南葉","weather":"芳野達郎"},{"id":"gEvykyRd98s","title":"【ライブ配信終了】最新天気ニュース・地震情報 2025年7月21日(月)／連休最終日も盛夏の暑さ　午後はゲリラ雷雨に注意〈ウェザーニュースLiVEモーニング・魚住茉由／芳野達郎〉","date":"2025-07-20","sec":12736,"caster":"魚住 茉由","weather":"芳野達郎"},{"id":"R7PlcbejXmY","title":"【ライブ】最新天気ニュース・地震情報 2025年7月21日(月)1:00〜／〈ウェザーニュースLiVE〉","date":"2025-07-20","sec":14127},{"id":"Q1W5SzOPhM0","title":"【ライブ配信終了】最新天気ニュース・地震情報 2025年7月20日(日)／連休最終日も酷暑に警戒〈ウェザーニュースLiVEムーン・岡本 結子リサ／森田 清輝〉","date":"2025-07-20","sec":18827,"caster":"岡本 結子 リサ","weather":"森田清輝"},{"id":"gbQ4OZ1dt58","title":"【ライブ配信終了】最新天気ニュース・地震情報 2025年7月20日(日)／10日ぶりに100地点超で猛暑日　連休最終日も酷暑に警戒〈ウェザーニュースLiVEイブニング・山岸 愛梨／森田 清輝〉","date":"2025-07-20","sec":11813,"caster":"山岸 愛梨","weather":"森田清輝"},{"id":"h4bg8jpJ8zI","title":"【ライブ配信終了】最新天気ニュース・地震情報 2025年7月20日(日)／三連休中日も真夏の暑さが続く　万全な熱中症対策を〈ウェザーニュースLiVEアフタヌーン・小川千奈／森田清輝〉","date":"2025-07-20","sec":12476,"caster":"小川 千奈","weather":"森田清輝"},{"id":"wFb32jnYu50","title":"【ライブ配信終了】最新天気ニュース・地震情報 2025年7月20日(日)／三連休中日も真夏の暑さが続く　万全な熱中症対策を〈ウェザーニュースLiVEコーヒータイム・松本真央／山口剛央〉","date":"2025-07-20","sec":12556,"caster":"松本 真央","weather":"山口剛央"},{"id":"rvvzxctpgkw","title":"【ライブ配信終了】最新天気ニュース・地震情報 2025年7月20日(日)／三連休中日も真夏の暑さが続く　万全な熱中症対策を〈ウェザーニュースLiVEサンシャイン・小林李衣奈／山口 剛央〉","date":"2025-07-19","sec":12543,"caster":"小林 李衣奈","weather":"山口剛央"},{"id":"75Osa1-ILbU","title":"【ライブ配信終了】最新天気ニュース・地震情報 2025年7月20日(日)／三連休中日も真夏の暑さが続く　万全な熱中症対策を〈ウェザーニュースLiVEモーニング・魚住茉由／山口剛央〉","date":"2025-07-19","sec":13332,"caster":"魚住 茉由","weather":"山口剛央"},{"id":"ivqcEQckgAc","title":"【ライブ配信終了】最新天気ニュース・地震情報 2025年7月20日(日)1:00〜／三連休中日も真夏の暑さが続く　万全な熱中症対策を〈ウェザーニュースLiVE〉","date":"2025-07-19","sec":13957},{"id":"uTn26mdK93E","title":"【ライブ配信終了】最新天気ニュース・地震情報 2025年7月19日(土)／三連休は暑さに注意〈ウェザーニュースLiVEムーン・駒木 結衣／森田 清輝〉","date":"2025-07-19","sec":18643,"caster":"駒木 結衣","weather":"森田清輝"},{"id":"9LywQhcCSm0","title":"【あなたも審査員！】伊勢の夜空に咲く最高峰の技。全国花火師ガチ勝負LIVE（伊勢市制施行20周年記念・第73回伊勢神宮奉納全国花火大会）","date":"2025-07-19","sec":7541},{"id":"kogjj8DWf1I","title":"【ライブ配信終了】最新天気ニュース・地震情報 2025年7月19日(土)／三連休初日は広い範囲で青空　夜も気温高く熱中症に注意〈ウェザーニュースLiVEイブニング・岡本結子リサ／森田 清輝〉","date":"2025-07-19","sec":11843,"caster":"岡本 結子 リサ","weather":"森田清輝"},{"id":"anG8iTX6jcI","title":"【ライブ配信終了】最新天気ニュース・地震情報 2025年7月19日(土)／三連休初日は本州各地で夏空　北海道は激しい雨に注意〈ウェザーニュースLiVEアフタヌーン・　戸北美月／森田清輝〉","date":"2025-07-19","sec":11737,"caster":"戸北 美月","weather":"森田清輝"},{"id":"zrhUYfeUKu8","title":"【ライブ配信終了】最新天気ニュース・地震情報 2025年7月19日(土)／三連休初日は本州各地で夏空　北海道は激しい雨に注意〈ウェザーニュースLiVEコーヒータイム・田辺真南葉／山口剛央〉","date":"2025-07-19","sec":12173,"caster":"田辺 真南葉","weather":"山口剛央"},{"id":"bFPbZsxW2kk","title":"【ライブカメラ】「白浜大浜ビーチ」@静岡県 下田市/2025年7月19日(土)　三連休初日","date":"2025-07-18","sec":42899},{"id":"BUkEdb0Kz30","title":"【ライブ配信終了】最新天気ニュース・地震情報 2025年7月19日(土)／三連休初日は本州各地で夏空　北海道は激しい雨に注意〈ウェザーニュースLiVEサンシャイン・魚住茉由／山口 剛央〉","date":"2025-07-18","sec":12581,"caster":"魚住 茉由","weather":"山口剛央"},{"id":"8XCoBcLJqT0","title":"【ライブ配信終了】最新天気ニュース・地震情報 2025年7月19日(土)／広く夏空に　北海道は強雨に注意〈ウェザーニュースLiVEモーニング・青原桃香／山口剛央〉","date":"2025-07-18","sec":12847,"caster":"青原 桃香","weather":"山口剛央"},{"id":"uxo4PQd2XV0","title":"【ライブ配信終了】最新天気ニュース・地震情報 2025年7月19日(土)1:00〜／三連休初日は本州各地で夏空　北海道は激しい雨に注意〈ウェザーニュースLiVE〉","date":"2025-07-18","sec":14131},{"id":"P8SL0RXxsY8","title":"【ライブ配信終了】最新天気ニュース・地震情報 2025年7月18日(金)21:30〜／西日本の太平洋側や北海道中心に雨〈ウェザーニュースLiVEムーン・駒木 結衣／宇野沢 達也〉","date":"2025-07-18","sec":12307,"caster":"駒木 結衣","weather":"宇野沢達也"},{"id":"zGCTMM2nqTg","title":"【JR東日本×ウェザーニュース】避暑旅タイアップ特別企画　第7回出演：駒木結衣、小川千奈","date":"2025-07-18","sec":2447,"caster":"小川 千奈"},{"id":"tBr8N3MPZfY","title":"【大雨ライブカメラ】線状降水帯のおそれ　各地の雨の様子／2025年7月18日(金)","date":"2025-07-18","sec":35576},{"id":"xIReWrAL05s","title":"【ライブ配信終了】最新天気ニュース・地震情報 2025年7月18日(金)／西日本の太平洋側を中心に大雨〈ウェザーニュースLiVEムーン・駒木 結衣／宇野沢 達也〉","date":"2025-07-18","sec":4569,"caster":"駒木 結衣","weather":"宇野沢達也"},{"id":"qvy-ZnMTkhc","title":"【ライブ配信終了】最新天気ニュース・地震情報 2025年7月18日(金)／九州は大雨に注意〈ウェザーニュースLiVEイブニング・戸北 美月／宇野沢 達也〉","date":"2025-07-18","sec":12094,"caster":"戸北 美月","weather":"宇野沢達也"},{"id":"nHFVA8aojbE","title":"【ライブ配信終了】最新天気ニュース・地震情報 2025年7月18日(金)／九州は大雨に注意・警戒〈ウェザーニュースLiVEアフタヌーン・　田辺真南葉／宇野沢達也〉","date":"2025-07-18","sec":12153,"caster":"田辺 真南葉","weather":"宇野沢達也"},{"id":"XY_UTq3KTS8","title":"【ライブ配信終了】最新天気ニュース・地震情報 2025年7月18日(金)／関東甲信など梅雨明け　四国や九州は大雨に注意・警戒〈ウェザーニュースLiVEコーヒータイム・松本真央／山口剛央〉","date":"2025-07-18","sec":12415,"caster":"松本 真央","weather":"山口剛央"},{"id":"ronEAL1EZ28","title":"【大雨／雨雲ライブ】線状降水帯発生のおそれ 西日本は大雨災害警戒　雨雲レーダー／大雨状況6画面監視ライブ　　2025年7月18日(金)","date":"2025-07-17","sec":42901},{"id":"AK9BdALUSvc","title":"【ライブ配信終了】最新天気ニュース・地震情報 2025年7月18日(金)／関東甲信など梅雨明けか　四国や九州は大雨に注意・警戒〈ウェザーニュースLiVEサンシャイン・小林李衣奈／山口 剛央〉","date":"2025-07-17","sec":12482,"caster":"小林 李衣奈","weather":"山口剛央"},{"id":"On-0YEooGIA","title":"【ライブ配信終了】最新天気ニュース・地震情報 2025年7月18日(金)／関東甲信など梅雨明けか　四国や九州は大雨に注意・警戒〈ウェザーニュースLiVEモーニング・青原桃香／山口剛央〉","date":"2025-07-17","sec":12322,"caster":"青原 桃香","weather":"山口剛央"},{"id":"CKSjegjJNSA","title":"【ライブ】最新天気ニュース・地震情報 2025年7月18日(金)1:00〜／関東甲信など梅雨明けか　四国や九州は大雨に注意・警戒〈ウェザーニュースLiVE〉","date":"2025-07-17","sec":13643},{"id":"EItbRDU4Lws","title":"【ライブ】最新天気ニュース・地震情報 2025年7月17日(木)／東海や西日本で大雨警戒〈ウェザーニュースLiVEムーン・駒木結衣／宇野沢達也〉","date":"2025-07-17","sec":20213,"caster":"駒木 結衣","weather":"宇野沢達也"},{"id":"1joBj-uIS6E","title":"【大雨／雨雲ライブ】線状降水帯のおそれ 東海から西日本は大雨災害警戒　雨雲レーダー／大雨状況6画面監視ライブ　　2025年7月17日(木)","date":"2025-07-17","sec":42901},{"id":"krUtT8UMIEI","title":"【ライブ配信終了】最新天気ニュース・地震情報 2025年7月17日(木)／東海〜九州太平洋側は大雨警戒　関東は天気回復へ〈ウェザーニュースLiVEイブニング・戸北美月／宇野沢達也〉","date":"2025-07-17","sec":11089,"caster":"戸北 美月","weather":"宇野沢達也"},{"id":"cVzbDojREtg","title":"【ライブ配信終了】最新天気ニュース・地震情報 2025年7月17日(木)／東海、近畿、四国太平洋側は大雨災害に警戒〈ウェザーニュースLiVEアフタヌーン・小川千奈／森田清輝〉","date":"2025-07-17","sec":12595,"caster":"小川 千奈","weather":"森田清輝"},{"id":"uzjJACnLDaE","title":"【ライブ配信終了】最新天気ニュース・地震情報 2025年7月17日(木)／東海、近畿、四国太平洋側は大雨災害に警戒〈ウェザーニュースLiVEコーヒータイム・小林李衣奈／芳野達郎〉","date":"2025-07-17","sec":12503,"caster":"小林 李衣奈","weather":"芳野達郎"},{"id":"dP6nLrutl4w","title":"【ライブ配信終了】最新天気ニュース・地震情報 2025年7月17日(木)／東海、近畿、四国太平洋側は大雨警戒　関東は天気回復へ〈ウェザーニュースLiVEサンシャイン・松本真央／芳野達郎〉","date":"2025-07-16","sec":12129,"caster":"松本 真央","weather":"芳野達郎"},{"id":"Afwu2114UQk","title":"【大雨／雨雲ライブ】東海から西日本で大雨災害に警戒　雨雲レーダー／大雨状況6画面監視ライブ　2025年7月16日(水)","date":"2025-07-16","sec":35425},{"id":"pGmOrGTf8o0","title":"【ライブ配信終了】最新天気ニュース・地震情報 2025年7月17日(木)／東海〜四国太平洋側は大雨警戒　関東は天気回復へ〈ウェザーニュースLiVEモーニング・福吉貴文／芳野達郎〉","date":"2025-07-16","sec":12110,"caster":"福吉 貴文","weather":"芳野達郎"},{"id":"ehRoujbbV2w","title":"【ライブ】最新天気ニュース・地震情報 2025年7月17日(木)1:00〜／東海や西日本で大雨に警戒〈ウェザーニュースLiVE〉","date":"2025-07-16","sec":14505},{"id":"duksfNiMCCY","title":"【ライブ】最新天気ニュース・地震情報 2025年7月16日(水)／東海、関東は大雨災害に警戒〈ウェザーニュースLiVEムーン・岡本結子／飯島栄一〉","date":"2025-07-16","sec":19183,"weather":"飯島栄一"},{"id":"ttoLtOibQtU","title":"【ライブ配信終了】最新天気ニュース・地震情報 2025年7月16日(水)／東海、関東は大雨災害に警戒〈ウェザーニュースLiVEイブニング・駒木 結衣／飯島 栄一〉","date":"2025-07-16","sec":12673,"caster":"駒木 結衣","weather":"飯島栄一"},{"id":"5LD2xHvwlvM","title":"【ライブ配信終了】最新天気ニュース・地震情報 2025年7月16日(水)／東海、関東は大雨災害に警戒〈ウェザーニュースLiVEアフタヌーン・山岸愛梨／飯島栄一〉","date":"2025-07-16","sec":11741,"caster":"山岸 愛梨","weather":"飯島栄一"},{"id":"WbehA7-CcDg","title":"【ライブ配信終了】最新天気ニュース・地震情報 2025年7月16日(水)／東海、関東は大雨災害に警戒〈ウェザーニュースLiVEコーヒータイム・小川千奈／本田竜也〉","date":"2025-07-16","sec":11090,"caster":"小川 千奈","weather":"本田竜也"},{"id":"584H-oJHT6I","title":"【ライブ配信終了】最新天気ニュース・地震情報 2025年7月16日(水)／東海、関東は大雨災害に警戒〈ウェザーニュースLiVEサンシャイン・青原桃香／本田竜也〉","date":"2025-07-15","sec":12107,"caster":"青原 桃香","weather":"本田竜也"},{"id":"aOpuDjROKQQ","title":"【ライブ配信終了】最新天気ニュース・地震情報 2025年7月16日(水)／東海、関東は大雨災害に警戒〈ウェザーニュースLiVEモーニング・魚住茉由／本田竜也〉","date":"2025-07-15","sec":11807,"caster":"魚住 茉由","weather":"本田竜也"},{"id":"6SPkyLxV2ow","title":"【ライブ】最新天気ニュース・地震情報 2025年7月16日(水)1:00〜／〈ウェザーニュースLiVE〉","date":"2025-07-15","sec":14262},{"id":"GRCbbz3535I","title":"【ライブ配信終了】最新天気ニュース・地震情報 2025年7月15日(火)／東海や関東で大雨警戒 西日本も太平洋側で強い雨〈ウェザーニュースLiVEムーン・岡本 結子リサ／飯島 栄一〉","date":"2025-07-15","sec":18284,"caster":"岡本 結子 リサ","weather":"飯島栄一"},{"id":"HAqxvEZm314","title":"【大雨／雨雲ライブ】東海・関東など大雨災害警戒　雨雲レーダー／大雨状況6画面監視ライブ　台風5号は北海道に上陸　2025年7月15日(火)","date":"2025-07-15","sec":42900},{"id":"fsoTMqMEobE","title":"【ライブ配信終了】最新天気ニュース・地震情報 2025年7月15日(火)／関東や東海は激しい雨に警戒　台風5号は温帯低気圧に〈ウェザーニュースLiVEイブニング・戸北美月／飯島栄一〉","date":"2025-07-15","sec":11417,"caster":"戸北 美月","weather":"飯島栄一"},{"id":"62vs7PE8sjU","title":"【ライブ配信終了】最新天気ニュース・地震情報 2025年7月15日(火)／関東や東海は激しい雨に警戒　台風5号は温帯低気圧に〈ウェザーニュースLiVEアフタヌーン・川畑玲／飯島栄一〉","date":"2025-07-15","sec":12815,"caster":"川畑 玲","weather":"飯島栄一"},{"id":"aTVZ7VzhH-0","title":"【ライブ配信終了】最新天気ニュース・地震情報 2025年7月15日(火)／関東や東海は激しい雨に警戒　台風5号は温帯低気圧に〈ウェザーニュースLiVEコーヒータイム・田辺真南葉／内藤邦裕〉","date":"2025-07-15","sec":12115,"caster":"田辺 真南葉","weather":"内藤邦裕"},{"id":"PBYV36Rm6qA","title":"【ライブカメラ】「白浜大浜ビーチ」@静岡県 下田市/2025年7月15日(火)","date":"2025-07-14","sec":42899},{"id":"eEGZvujNe4M","title":"【最新大雨ニュース】東海・関東などで大雨に厳重警戒 線状降水帯発生の可能性／台風5号は北海道に上陸  2025年7月15日(水)","date":"2025-07-14","sec":42899},{"id":"KxO0uZ9cIPg","title":"【ライブ配信終了】最新天気ニュース・地震情報 2025年7月15日(火)／関東や東海は激しい雨に警戒　台風5号最新情報〈ウェザーニュースLiVEサンシャイン・松本真央／内藤邦裕〉","date":"2025-07-14","sec":12061,"caster":"松本 真央","weather":"内藤邦裕"},{"id":"Ye_06cA7NtM","title":"【ライブ配信終了】最新天気ニュース・地震情報 2025年7月15日(火)／関東や東海は激しい雨に警戒　台風5号は北海道に上陸〈ウェザーニュースLiVEモーニング・魚住茉由／内藤邦裕〉","date":"2025-07-14","sec":12493,"caster":"魚住 茉由","weather":"内藤邦裕"},{"id":"SaT388MjFP0","title":"【台風／大雨ニュース】東海・関東など東日本太平洋側で大雨のおそれ 線状降水帯発生の可能性／台風5号は北海道に上陸か  2025年7月14日(月)","date":"2025-07-14","sec":42899},{"id":"Ot24O85uXtM","title":"【ライブ配信終了】最新天気ニュース・地震情報 2025年7月15日(火)1:00〜／〈ウェザーニュースLiVE〉","date":"2025-07-14","sec":12253},{"id":"IfkyMejtgY4","title":"【ライブ配信終了】最新天気ニュース・地震情報 2025年7月14日(月)／近畿や東海は大雨に警戒　北海道に台風5号上陸へ〈ウェザーニュースLiVEムーン・岡本結子リサ／山口 剛央〉","date":"2025-07-14","sec":19959,"caster":"岡本 結子 リサ","weather":"山口剛央"},{"id":"Tz5DiYhIJMk","title":"【ライブ配信終了】最新天気ニュース・地震情報 2025年7月14日(月)／西日本で大雨のおそれ　関東・東北に台風接近〈ウェザーニュースLiVEイブニング・駒木 結衣／山口 剛央〉","date":"2025-07-14","sec":12611,"caster":"駒木 結衣","weather":"山口剛央"},{"id":"3SJncIgj9Ng","title":"【ライブ配信終了】最新天気ニュース・地震情報 2025年7月14日(月)／西日本で大雨のおそれ　台風5号が接近・北上中〈ウェザーニュースLiVEアフタヌーン・戸北美月／山口剛央〉","date":"2025-07-14","sec":11611,"caster":"戸北 美月","weather":"山口剛央"},{"id":"oFyTILIkfTg","title":"【ライブ配信終了】最新天気ニュース・地震情報 2025年7月14日(月)／台風5号 関東・東北に台風接近　西日本で大雨のおそれ〈ウェザーニュースLiVEコーヒータイム・青原桃香／芳野達郎〉","date":"2025-07-14","sec":12111,"caster":"青原 桃香","weather":"芳野達郎"},{"id":"Bi7-kOoq0gY","title":"【雨風ライブカメラ】台風5号(ナーリー)関東・東北に接近　沿岸では一時暴風も ／千葉県南房総市 2025.7.14","date":"2025-07-13","sec":42900},{"id":"aS4F3gLQWOA","title":"【ライブ配信終了】最新天気ニュース・地震情報 2025年7月13日(日)／熱帯低気圧が接近 週明けは大雨警戒〈ウェザーニュースLiVEイブニング・白井ゆかり／森田清輝〉","date":"2025-07-13","sec":9783,"caster":"白井 ゆかり","weather":"森田清輝"},{"id":"ulaaqFGlLoI","title":"【ライブカメラ】「白浜大浜ビーチ」台風5号関東最接近　@静岡県 下田市/2025年7月14日(月)","date":"2025-07-13","sec":42899},{"id":"hn978HQCgjw","title":"【ライブ配信終了】最新天気ニュース・地震情報 2025年7月14日(月)／西日本で大雨のおそれ　関東・東北に台風接近〈ウェザーニュースLiVEサンシャイン・魚住茉由／芳野達郎〉","date":"2025-07-13","sec":12336,"caster":"魚住 茉由","weather":"芳野達郎"},{"id":"cEKide-YfHU","title":"【火山カメラ】霧島山・新燃岳ライブカメラ　宮崎県都城市より 2025.7.14","date":"2025-07-13","sec":8006},{"id":"iNoNTJRo7dc","title":"【ライブ配信終了】最新天気ニュース・地震情報 2025年7月14日(月)／関東・東北に台風5号接近、西日本で大雨のおそれ　〈ウェザーニュースLiVEモーニング・小川千奈／芳野達郎〉","date":"2025-07-13","sec":12143,"caster":"小川 千奈","weather":"芳野達郎"},{"id":"aKwKs9vc6Vc","title":"【火山カメラ】霧島山・新燃岳ライブカメラ　連続噴火が継続中　宮崎県都城市より 2025.7.13夜","date":"2025-07-13","sec":32871},{"id":"ZOfcHxfb_eQ","title":"【ライブカメラ】幕張から東京・千葉の夜景／千葉県千葉市美浜区 ウェザーニュースお天気カメラ 2025年7月13日","date":"2025-07-13","sec":34633},{"id":"KuykDAaP_Zg","title":"【ライブ配信終了】最新天気ニュース・地震情報 2025年7月14日(月)1:00〜／西日本で大雨のおそれ　関東・東北に台風接近〈ウェザーニュースLiVE〉","date":"2025-07-13","sec":14519},{"id":"z1LDvpQiPNQ","title":"【雨風ライブカメラ】台風5号(ナーリー)小笠原近海を北上・14日関東最接近／東京都母島より 2025.7.13夜","date":"2025-07-13","sec":20295},{"id":"bgytnHLNBbI","title":"【ライブ配信終了】最新天気ニュース・地震情報 2025年7月13日(日)／あす台風５号は関東に接近　週明けは大雨警戒〈ウェザーニュースLiVEムーン・山岸 愛梨／森田 清輝〉","date":"2025-07-13","sec":18275,"caster":"山岸 愛梨","weather":"森田清輝"},{"id":"jCUVXwfqQ-E","title":"【ライブ配信終了】最新天気ニュース・地震情報 2025年7月13日(日)／熱帯低気圧が接近 週明けは大雨警戒〈ウェザーニュースLiVEアフタヌーン・青原桃香／森田 清輝〉","date":"2025-07-13","sec":11713,"caster":"青原 桃香","weather":"森田清輝"},{"id":"Grpq1fKr6Wc","title":"【ライブ配信終了】最新天気ニュース・地震情報 2025年7月13日(日)／熱帯低気圧が接近 週明けは大雨警戒〈ウェザーニュースLiVEコーヒータイム・田辺真南葉／山口剛央〉","date":"2025-07-13","sec":11497,"caster":"田辺 真南葉","weather":"山口剛央"},{"id":"9VIGx1YGHWI","title":"【雨風ライブカメラ】台風5号(ナーリー)発生・関東で雨風強まる可能性　東京都母島より 2025.7.13","date":"2025-07-12","sec":42901},{"id":"UAJXUTfgGyI","title":"【火山カメラ】霧島山・新燃岳ライブカメラ　宮崎県都城市より 2025.7.13","date":"2025-07-12","sec":42832},{"id":"7h-W6vN7BKQ","title":"【ビーチライブカメラ】「白浜大浜ビーチ」@静岡県 下田市/2025年7月13日(日)","date":"2025-07-12","sec":42899},{"id":"GwJHf2zTFc4","title":"【ライブ配信終了】最新天気ニュース・地震情報 2025年7月13日(日)／台風5号が接近 週明けは大雨警戒〈ウェザーニュースLiVEサンシャイン・松本真央／山口 剛央〉","date":"2025-07-12","sec":12202,"caster":"松本 真央","weather":"山口剛央"},{"id":"bSVXZ61AF-E","title":"【ライブ配信終了】最新天気ニュース・地震情報 2025年7月13日(日)／台風5号が接近 週明けは大雨警戒〈ウェザーニュースLiVEモーニング・小川千奈／山口剛央〉","date":"2025-07-12","sec":11986,"caster":"小川 千奈","weather":"山口剛央"},{"id":"yQPBEeVBZV0","title":"【ライブ配信終了】最新天気ニュース・地震情報 2025年7月13日(日)1:00〜／〈ウェザーニュースLiVE〉","date":"2025-07-12","sec":15545},{"id":"IcaaHaA7qig","title":"【ライブ配信終了】最新天気ニュース・地震情報 2025年7月12日(土)／あすは全国的に厳しい暑さ　関東も夏の体感が戻る〈ウェザーニュースLiVEムーン・駒木 結衣／森田 清輝〉","date":"2025-07-12","sec":17025,"caster":"駒木 結衣","weather":"森田清輝"},{"id":"uzA6trKYZ20","title":"【ライブ配信終了】最新天気ニュース・地震情報 2025年7月12日(土)／24時間以内に台風発生の可能性〈ウェザーニュースLiVEイブニング・岡本結子リサ／森田清輝〉","date":"2025-07-12","sec":10152,"caster":"岡本 結子 リサ","weather":"森田清輝"},{"id":"B29J4V_EcKg","title":"【ライブ配信終了】最新天気ニュース・地震情報 2025年7月12日(土)／西日本や東海は猛暑　関東と東北太平洋側は雲が主役〈ウェザーニュースLiVEアフタヌーン・田辺 真南葉／森田 清輝〉","date":"2025-07-12","sec":11731,"caster":"田辺 真南葉","weather":"森田清輝"},{"id":"yePo6QDiiFQ","title":"【ライブ】ブルーインパルス大阪・関西万博 展示飛行 ライブカメラ  2025年7月12日(土) #ブルーインパルス #ライブカメラ","date":"2025-07-12","sec":3859},{"id":"oALwAT-NESw","title":"【ライブ配信終了】最新天気ニュース・地震情報 2025年7月12日(土)／西日本や東海は猛暑　関東と東北太平洋側は雲が主役〈ウェザーニュースLiVEコーヒータイム・松本真央／山口剛央〉","date":"2025-07-12","sec":12051,"caster":"松本 真央","weather":"山口剛央"},{"id":"sjggE9oiQbs","title":"【ダイワハウス×ウェザーニュース特別番組】『災害級の暑さ』が日常になる時代の暮らし／2025年7月12日(土) 10:00〜","date":"2025-07-12","sec":2757},{"id":"CMO8oUuVM4U","title":"【ビーチライブカメラ】「白浜大浜ビーチ」@静岡県 下田市/2025年7月12日(土)","date":"2025-07-11","sec":42899},{"id":"-2Vhhqmo_Ys","title":"【火山カメラ】霧島山・新燃岳ライブカメラ　連続噴火が継続中　宮崎県都城市より 2025.7.12","date":"2025-07-11","sec":42901},{"id":"3RRGPgiLESI","title":"【ライブ配信終了】最新天気ニュース・地震情報 2025年7月12日(土)／西日本は猛暑と強雨が混在 関東や東北太平洋側は雲が主役〈ウェザーニュースLiVEサンシャイン・小川千奈／山口剛央〉","date":"2025-07-11","sec":12246,"caster":"小川 千奈","weather":"山口剛央"},{"id":"TngseKL5ue0","title":"【ライブ配信終了】最新天気ニュース・地震情報 2025年7月12日(土)／西日本は猛暑と強雨に注意 関東や東北太平洋側は雲が主役〈ウェザーニュースLiVEモーニング・魚住茉由／山口剛央〉","date":"2025-07-11","sec":12247,"caster":"魚住 茉由","weather":"山口剛央"},{"id":"P0Pjj4rUqio","title":"【ライブカメラ】幕張から東京・千葉の夜景／千葉県千葉市美浜区 ウェザーニュースお天気カメラ 2025年7月11日","date":"2025-07-11","sec":30411},{"id":"0omdyRwHvDg","title":"【ライブ配信終了】最新天気ニュース・地震情報 2025年7月12日(土)1:00〜／〈ウェザーニュースLiVE〉","date":"2025-07-11","sec":14236},{"id":"ELmwNl6tzSM","title":"【ライブ】最新天気ニュース・地震情報 2025年7月11日(金)／西日本太平洋側を中心に雨〈ウェザーニュースLiVEムーン・駒木 結衣／宇野沢 達也〉","date":"2025-07-11","sec":12711,"caster":"駒木 結衣","weather":"宇野沢達也"},{"id":"VZk7gjam99U","title":"【天体ライブ】7月の満月 バックムーン(Buck Moon／男鹿月) 2025 ライブカメラ 北海道・なよろ市立天文台きたすばるより生中継 /2025年7月11日(金)","date":"2025-07-11","sec":6759},{"id":"Lybr1X_QgTY","title":"【ライブ配信終了】最新天気ニュース・地震情報 2025年7月11日(金)／西日本は強雨注意〈ウェザーニュースLiVEイブニング・岡本結子リサ／宇野沢達也〉","date":"2025-07-11","sec":9868,"caster":"岡本 結子 リサ","weather":"宇野沢達也"},{"id":"h3OLuzkwvCY","title":"【JR東日本×ウェザーニュース】避暑旅タイアップ特別企画　第6回出演：駒木結衣","date":"2025-07-11","sec":2266,"caster":"駒木 結衣"},{"id":"8hafcTiJbxg","title":"【ライブ配信終了】最新天気ニュース・地震情報 2025年7月11日(金)／西日本太平洋側を中心に雨〈ウェザーニュースLiVEムーン・駒木 結衣／宇野沢 達也〉","date":"2025-07-11","sec":4359,"caster":"駒木 結衣","weather":"宇野沢達也"},{"id":"9zL_Se6pSqg","title":"【ライブ配信終了】最新天気ニュース・地震情報 2025年7月11日(金)／関東は暑さ落ち着く・西日本は強雨注意〈ウェザーニュースLiVEアフタヌーン・白井ゆかり／宇野沢達也〉","date":"2025-07-11","sec":12620,"caster":"白井 ゆかり","weather":"宇野沢達也"},{"id":"QK6tRF6-ti4","title":"【ライブ配信終了】最新天気ニュース・地震情報 2025年7月11日(金)／関東は暑さ落ち着く・西日本は強雨注意〈ウェザーニュースLiVEコーヒータイム・田辺真南葉／山口剛央〉","date":"2025-07-11","sec":12465,"caster":"田辺 真南葉","weather":"山口剛央"},{"id":"6Hky8XF3-mc","title":"【気候変動番組】100年天気予報〜温暖化で変わる台風 その先にある日本のリスク〜/2025年7月11日(金)12:00~/魚住茉由・吉良真由子","date":"2025-07-11","sec":2342,"caster":"魚住 茉由"},{"id":"Y99PTGMzHtY","title":"【ライブ配信終了】最新天気ニュース・地震情報 2025年7月11日(金)／関東は暑さ落ち着く・西日本は強雨注意〈ウェザーニュースLiVEサンシャイン・小川千奈／山口剛央〉","date":"2025-07-10","sec":12330,"caster":"小川 千奈","weather":"山口剛央"},{"id":"nyQ4DanEUf8","title":"【ライブ配信終了】最新天気ニュース・地震情報 2025年7月11日(金)／関東は暑さ落ち着く・西日本は強雨注意〈ウェザーニュースLiVEモーニング・福吉貴文／山口剛央〉","date":"2025-07-10","sec":12313,"caster":"福吉 貴文","weather":"山口剛央"},{"id":"brfM1-p0B-s","title":"【ライブ】最新天気ニュース・地震情報 2025年7月11日(金)1:00〜／〈ウェザーニュースLiVE〉","date":"2025-07-10","sec":15811},{"id":"i-dnGqczzx0","title":"【ライブ配信終了】最新天気ニュース・地震情報 2025年7月10日(木)／関東は梅雨空が戻る　西日本も強雨に注意〈ウェザーニュースLiVEムーン・岡本結子リサ／本田 竜也〉","date":"2025-07-10","sec":16373,"caster":"岡本 結子 リサ","weather":"本田竜也"},{"id":"qL8AFKZMPoc","title":"【雨雲／落雷ライブ】ゲリラ雷雨情報　雨雲レーダー／落雷レーダー監視　関東は線状降水帯発生の可能性　2025年7月10日(木)","date":"2025-07-10","sec":22416},{"id":"uuSevHUv_wg","title":"【ライブ】関東雷雨ライブカメラ／関東で大規模なゲリラ雷雨 2025年7月10日(木)","date":"2025-07-10","sec":9965},{"id":"gQv0FtnAlA8","title":"【ライブ】東京 目黒川ライブカメラ 氾濫のおそれ 警戒レベル4相当の氾濫危険情報発表 /2025年7月10日(木)","date":"2025-07-10","sec":5627},{"id":"hCpO_T6iBOE","title":"【ライブ配信終了】関東 大規模ゲリラ雷雨・気象庁「線状降水帯発生のおそれ」／最新天気ニュース・地震情報 2025年7月10日(木)〈ウェザーニュースLiVEイブニング・駒木 結衣／本田 竜也〉","date":"2025-07-10","sec":10917,"caster":"駒木 結衣","weather":"本田竜也"},{"id":"aXpifTQh3WQ","title":"【ライブ配信終了】最新天気ニュース・地震情報 2025年7月10日(木)／関東は梅雨空が戻る　西日本も強雨に注意〈ウェザーニュースLiVEアフタヌーン・戸北 美月／本田 竜也〉","date":"2025-07-10","sec":13037,"caster":"戸北 美月","weather":"本田竜也"},{"id":"6qrvHBaRJDk","title":"【ライブ配信終了】最新天気ニュース・地震情報 2025年7月10日(木)／関東や西日本で強雨・雷雨に注意〈ウェザーニュースLiVEコーヒータイム・松本 真央／山口 剛央〉","date":"2025-07-10","sec":12461,"caster":"松本 真央","weather":"山口剛央"},{"id":"-UHhFkxu0LQ","title":"【ライブ配信終了】最新天気ニュース・地震情報 2025年7月10日(木)／関東は梅雨空が戻る　西日本も強雨に注意〈ウェザーニュースLiVEサンシャイン・魚住 茉由／山口 剛央〉","date":"2025-07-09","sec":11825,"caster":"魚住 茉由","weather":"山口剛央"},{"id":"AQZpjIE6M-c","title":"【ライブ配信終了】最新天気ニュース・地震情報 2025年7月10日(木)／関東は梅雨空が戻る　西日本も強雨に注意〈ウェザーニュースLiVEモーニング・小林李衣奈／山口剛央〉","date":"2025-07-09","sec":12120,"caster":"小林 李衣奈","weather":"山口剛央"},{"id":"s09R1q--Sc8","title":"【ライブカメラ】幕張から東京・千葉の夜景／千葉県千葉市美浜区 ウェザーニュースお天気カメラ 2025年7月9日-10日","date":"2025-07-09","sec":26115},{"id":"1AWDQRdFx-0","title":"【ライブ】最新天気ニュース・地震情報 2025年7月10日(木)1:00〜／関東は梅雨空戻り　西日本も強雨に注意〈ウェザーニュースLiVE〉","date":"2025-07-09","sec":14421}]