{"updated":"2026-07-02T09:46","items":[{"source":"ウェザーニュース公式","platform":"site","title":"来週にかけて梅雨前線が北上傾向　西日本は熱帯夜となるところも","url":"https://weathernews.jp/news/202607/020321/","thumb":"https://smtgvs.cdn.weathernews.jp/s/topics/thumb/article/202607020321_top_img_A_320x240.jpg?1782982972","date":"2026-07-02T18:00"},{"source":"ウェザーニュース公式","platform":"site","title":"今夜は北陸や東北で強雨に注意　明日は関東甲信で天気急変の可能性も","url":"https://weathernews.jp/news/202607/020301/","thumb":"https://smtgvs.cdn.weathernews.jp/s/topics/thumb/article/202607020301_top_img_A_320x240.jpg?1782979969","date":"2026-07-02T17:00"},{"source":"ウェザーニュース公式","platform":"site","title":"明日7月3日(金)の天気予報　関東甲信や東北は天気急変に注意　西日本は暑さ対策を","url":"https://weathernews.jp/news/202607/020221/","thumb":"https://smtgvs.cdn.weathernews.jp/s/topics/thumb/article/202607020221_top_img_A_320x240.jpg?1782978894","date":"2026-07-02T16:50"},{"source":"ウェザーニュース公式","platform":"site","title":"線状降水帯で九州北部に記録的大雨　筑後川水系に沿って冠水被害","url":"https://weathernews.jp/news/202607/020211/","thumb":"https://smtgvs.cdn.weathernews.jp/s/topics/thumb/article/202607020211_top_img_A_320x240.jpg?1782977834","date":"2026-07-02T16:40"},{"source":"ウェザーニュース公式","platform":"site","title":"7月3日(金)　各地の気温変化と最適な服装","url":"https://weathernews.jp/news/202607/020241/","thumb":"https://smtgvs.cdn.weathernews.jp/s/topics/thumb/article/202607020241_top_img_A_320x240.jpg?1782977699","date":"2026-07-02T16:35"},{"source":"ウェザーニュース公式","platform":"site","title":"台風9号(バービー)　急発達しながら日本のはるか南の海上を西進　今後の動向に注意","url":"https://weathernews.jp/news/202607/020271/","thumb":"https://smtgvs.cdn.weathernews.jp/s/topics/thumb/article/202607020271_top_img_A_320x240.jpg?1782985390","date":"2026-07-02T16:21"},{"source":"ウェザーニュース公式","platform":"site","title":"気象庁1か月予報　広い範囲で高温傾向　厳しい暑さに要注意","url":"https://weathernews.jp/news/202607/020261/","thumb":"https://smtgvs.cdn.weathernews.jp/s/topics/thumb/article/202607020261_top_img_A_320x240.jpg?1782974219","date":"2026-07-02T15:35"},{"source":"ウェザーニュース公式","platform":"youtube","title":"【台風9号（バービー）】急発達しながら西進　7月半ば頃から南西諸島に影響か #通勤タイパ #news #台風9号","url":"https://www.youtube.com/watch?v=wQEOk3WNTcs","thumb":"wQEOk3WNTcs","date":"2026-07-02T07:49:41+00:00"},{"source":"ウェザーニュース公式","platform":"youtube","title":"明日もファイト！7月2日 #通勤タイパ #駒木結衣 #ファイト","url":"https://www.youtube.com/watch?v=13bNNtTN5Kg","thumb":"13bNNtTN5Kg","date":"2026-07-02T07:30:38+00:00"},{"source":"ウェザーニュース公式","platform":"youtube","title":"【7月3日(金)の天気予報】東北南部から中部は天気急変に注意　西日本晴れて気温上昇 #通勤タイパ #news #明日の天気","url":"https://www.youtube.com/watch?v=cF1eBh1hNiM","thumb":"cF1eBh1hNiM","date":"2026-07-02T07:30:30+00:00"},{"source":"ウェザーニュース公式","platform":"youtube","title":"今日も一日お疲れ様でした☔️7月2日 #通勤タイパ #小林李衣奈 #おつかれ","url":"https://www.youtube.com/watch?v=rokRbOsrFm0","thumb":"rokRbOsrFm0","date":"2026-07-02T07:00:15+00:00"},{"source":"ウェザーニュース公式","platform":"youtube","title":"【ライブ】最新天気ニュース・地震情報 2026年7月3日(金)／12:00〜「100年天気予報」〈ウェザーニュースLiVEコーヒータイム・福吉貴文／山口剛央〉","url":"https://www.youtube.com/watch?v=GIZHijqUFH8","thumb":"GIZHijqUFH8","date":"2026-07-02T04:25:57+00:00"},{"source":"ウェザーニュース公式","platform":"youtube","title":"【週間天気】週末の雨のあとは極端な高温に　前線の動きによる天気の急変に警戒を","url":"https://www.youtube.com/watch?v=LNAq7Ugpl0M","thumb":"LNAq7Ugpl0M","date":"2026-07-02T04:14:54+00:00"},{"source":"ウェザーニュース公式","platform":"youtube","title":"【週間天気予報】土曜日は九州で強雨や大雨に注意　週中頃から晴れて気温上昇 #通勤タイパ #news #週間天気","url":"https://www.youtube.com/watch?v=YFnZzzmQPk4","thumb":"YFnZzzmQPk4","date":"2026-07-02T04:07:52+00:00"},{"source":"ウェザーニュース公式","platform":"youtube","title":"【週間天気】週末は広い範囲で雨具の出番となりそう🐸☔️#通勤タイパ #今週の天気 #松本真央","url":"https://www.youtube.com/watch?v=2C-ykoLu08g","thumb":"2C-ykoLu08g","date":"2026-07-02T03:00:02+00:00"},{"source":"ウェザーニュース公式","platform":"youtube","title":"【大雨情報】線状降水帯発生していた九州から土砂崩れの報告相次ぐ  #通勤タイパ #news #大雨","url":"https://www.youtube.com/watch?v=BnRTZWFWhKc","thumb":"BnRTZWFWhKc","date":"2026-07-02T02:52:59+00:00"},{"source":"ウェザーニュース公式","platform":"youtube","title":"【台風9号発生 2026年】急激に発達し「非常に強い」勢力へ　今後の進路を気象予報士が解説","url":"https://www.youtube.com/watch?v=77pgrN6CG8c","thumb":"77pgrN6CG8c","date":"2026-07-02T02:22:04+00:00"},{"source":"ウェザーニュース公式","platform":"youtube","title":"【台風9号発生】急発達しながら沖縄に接近か　来週後半は注意警戒 #通勤タイパ #news #台風","url":"https://www.youtube.com/watch?v=zwfqvpclyXc","thumb":"zwfqvpclyXc","date":"2026-07-02T02:08:15+00:00"},{"source":"ウェザーニュース公式","platform":"youtube","title":"【大雨警戒】線状降水帯が発生した九州で土砂崩れ相次ぐ…雨が止んでも警戒を 土砂災害の前兆とは？","url":"https://www.youtube.com/watch?v=QNTZSbeU2Ns","thumb":"QNTZSbeU2Ns","date":"2026-07-02T00:54:12+00:00"},{"source":"ウェザーニュース公式","platform":"youtube","title":"【関東の天気】関東で強い雨 一部では土砂降りに  #通勤タイパ #news #大雨","url":"https://www.youtube.com/watch?v=09Qk_OJ7xRE","thumb":"09Qk_OJ7xRE","date":"2026-07-01T23:38:00+00:00"},{"source":"ウェザーニュース公式","platform":"youtube","title":"【関東の天気】通勤時間帯に強い雨、一部では土砂降りも。午後の雨の見通しは？","url":"https://www.youtube.com/watch?v=IXLFr8odCwc","thumb":"IXLFr8odCwc","date":"2026-07-01T23:19:33+00:00"},{"source":"ウェザーニュース公式","platform":"youtube","title":"【ライブ】最新天気ニュース・地震情報 2026年7月2日(木) ／東北〜九州の広範囲で雨〈ウェザーニュースLiVEイブニング・戸北美月／本田竜也〉","url":"https://www.youtube.com/watch?v=Q6-RTdjHC2E","thumb":"Q6-RTdjHC2E","date":"2026-07-01T11:17:09+00:00"}]}