{"updated":"2026-07-01T17:32","items":[{"source":"ウェザーニュース公式","platform":"site","title":"長崎県・佐賀県で線状降水帯による大雨 災害発生に厳重警戒","url":"https://weathernews.jp/news/202607/020031/","thumb":"https://smtgvs.cdn.weathernews.jp/s/topics/thumb/article/202607020031_top_img_A_320x240.jpg?1782922862","date":"2026-07-02T00:38"},{"source":"ウェザーニュース公式","platform":"site","title":"長崎県・佐賀県・福岡県・大分県で線状降水帯が発生のおそれ 大雨に厳重警戒","url":"https://weathernews.jp/news/202607/010281/","thumb":"https://smtgvs.cdn.weathernews.jp/s/topics/thumb/article/202607010281_top_img_A_320x240.jpg?1782925046","date":"2026-07-01T21:38"},{"source":"ウェザーニュース公式","platform":"site","title":"岩手県沖でM6.0の地震　最大震度4　津波の心配なし","url":"https://weathernews.jp/news/202607/012108quake/","thumb":"https://smtgvs.cdn.weathernews.jp/s/topics/thumb/article/202607012108quake_top_img_A_320x240.jpg?1782908974","date":"2026-07-01T21:14"},{"source":"ウェザーニュース公式","platform":"site","title":"明日7月2日(木)の天気予報　東北から九州の広範囲で雨　関東は午前が雨のピーク","url":"https://weathernews.jp/news/202607/010221/","thumb":"https://smtgvs.cdn.weathernews.jp/s/topics/thumb/article/202607010221_top_img_A_320x240.jpg?1782892833","date":"2026-07-01T16:55"},{"source":"ウェザーニュース公式","platform":"site","title":"7月2日(木)　各地の気温変化と最適な服装","url":"https://weathernews.jp/news/202607/010231/","thumb":"https://smtgvs.cdn.weathernews.jp/s/topics/thumb/article/202607010231_top_img_A_320x240.jpg?1782892732","date":"2026-07-01T16:50"},{"source":"ウェザーニュース公式","platform":"youtube","title":"【地震ライブ】緊急地震速報 24時間リアルタイム配信中 ウェザーニュース／Earthquake Alert Japan Live","url":"https://www.youtube.com/watch?v=k5QWgryzTy4","thumb":"k5QWgryzTy4","date":"2026-07-01T16:18:15+00:00"},{"source":"ウェザーニュース公式","platform":"site","title":"週間天気予報　週末も強雨や雷雨に注意　蒸し暑さが続く","url":"https://weathernews.jp/news/202607/010191/","thumb":"https://smtgvs.cdn.weathernews.jp/s/topics/thumb/article/202607010191_top_img_A_320x240.jpg?1782885705","date":"2026-07-01T14:55"},{"source":"ウェザーニュース公式","platform":"youtube","title":"【海外気象ニュース】ヨーロッパで記録的熱波　死者1000名超の猛暑をもたらす「ヒートドーム現象」を徹底解説","url":"https://www.youtube.com/watch?v=CYoGa3KGeeI","thumb":"CYoGa3KGeeI","date":"2026-07-01T14:51:56+00:00"},{"source":"ウェザーニュース公式","platform":"youtube","title":"【ライブ】最優秀オールフリー賞決定戦～オールフリーを飲んで 暑い夏を乗り切りろう〜 出演：駒木結衣／2026年7月1日(水)22:00〜〈サントリー×ウェザーニュース〉","url":"https://www.youtube.com/watch?v=6lFUcGxUPUw","thumb":"6lFUcGxUPUw","date":"2026-07-01T13:24:41+00:00"},{"source":"ウェザーニュース公式","platform":"youtube","title":"【大雨情報】長崎県で線状降水帯が発生のおそれ 大雨に厳重警戒","url":"https://www.youtube.com/watch?v=9WGks0myWkk","thumb":"9WGks0myWkk","date":"2026-07-01T13:19:26+00:00"},{"source":"ウェザーニュース公式","platform":"site","title":"早くもカブトムシ・クワガタが出現　見た人の6割超が\"例年より早い\"と実感","url":"https://weathernews.jp/news/202606/300211/","thumb":"https://smtgvs.cdn.weathernews.jp/s/topics/thumb/article/202606300211_top_img_A_320x240.jpg?1782879348","date":"2026-07-01T13:14"},{"source":"ウェザーニュース公式","platform":"youtube","title":"【最大震度4】岩手県沖で地震発生 マグニチュード6.0 津波の心配なし","url":"https://www.youtube.com/watch?v=RBdAGseoG_w","thumb":"RBdAGseoG_w","date":"2026-07-01T12:46:40+00:00"},{"source":"ウェザーニュース公式","platform":"youtube","title":"【Pontaパス天気予報】夕日夕焼けと週間天気をお届け(2026年7月1日配信) #夕焼けハッピーパス","url":"https://www.youtube.com/watch?v=ls67-qKnvPg","thumb":"ls67-qKnvPg","date":"2026-07-01T11:39:35+00:00"},{"source":"ウェザーニュース公式","platform":"youtube","title":"【大雨警戒】明日の午前中にかけて西日本は要警戒　九州で線状降水帯発生の可能性も","url":"https://www.youtube.com/watch?v=p1971AEqBss","thumb":"p1971AEqBss","date":"2026-07-01T11:23:40+00:00"},{"source":"ウェザーニュース公式","platform":"youtube","title":"【空のあとがき】白井キャスターの気になるリポートは？ #通勤タイパ #白井ゆかり","url":"https://www.youtube.com/watch?v=-zVjSH-4_r4","thumb":"-zVjSH-4_r4","date":"2026-07-01T10:00:23+00:00"},{"source":"ウェザーニュース公式","platform":"youtube","title":"明日もファイト〜！7月1日 #通勤タイパ #戸北美月 #ファイト","url":"https://www.youtube.com/watch?v=o_3y94yItkw","thumb":"o_3y94yItkw","date":"2026-07-01T09:15:02+00:00"},{"source":"ウェザーニュース公式","platform":"youtube","title":"【雨情報】明日の関東は通勤通学の時間に激しい雨のおそれ","url":"https://www.youtube.com/watch?v=pQN029Yq3LU","thumb":"pQN029Yq3LU","date":"2026-07-01T09:07:52+00:00"},{"source":"ウェザーニュース公式","platform":"youtube","title":"今日もお疲れさまでした！7月1日 #通勤タイパ #小川千奈 #お疲れさま","url":"https://www.youtube.com/watch?v=RWF3rgyVKRo","thumb":"RWF3rgyVKRo","date":"2026-07-01T08:42:06+00:00"},{"source":"ウェザーニュース公式","platform":"youtube","title":"【週間天気】7月2日〜3日は要注意/前線と低気圧の影響で大雨の可能性","url":"https://www.youtube.com/watch?v=F6O-8iHMG48","thumb":"F6O-8iHMG48","date":"2026-07-01T04:03:48+00:00"},{"source":"ウェザーニュース公式","platform":"youtube","title":"【週間天気】この先、西日本を中心に大雨に注意⚠️☔️#通勤タイパ #今週の天気 #岡本結子","url":"https://www.youtube.com/watch?v=MJpIGZdx0NA","thumb":"MJpIGZdx0NA","date":"2026-07-01T04:00:14+00:00"},{"source":"ウェザーニュース公式","platform":"youtube","title":"【台風発生予想】2つの熱帯低気圧が台風へ発達する見込み 片方は今後強い勢力へ 進路注意（2026年7月1日 11時更新）","url":"https://www.youtube.com/watch?v=ruH61NOezgk","thumb":"ruH61NOezgk","date":"2026-07-01T02:16:40+00:00"},{"source":"ウェザーニュース公式","platform":"youtube","title":"【ライブ】最新天気ニュース・地震情報 2026年7月2日(木)1:00〜／長崎・佐賀で線状降水帯発生　土砂災害・河川氾濫に警戒〈ウェザーニュースLiVE〉","url":"https://www.youtube.com/watch?v=ilqvhgQlIk8","thumb":"ilqvhgQlIk8","date":"2026-06-30T15:27:51+00:00"}]}